{"Data":[{"Method":"Feet follow hands","Name":"LOBSTA","Grade":"6C+","UserGrade":null,"MoonBoardConfiguration":{"Id":1,"Description":"40° MoonBoard","LowGrade":null,"HighGrade":null},"MoonBoardConfigurationId":0,"Setter":{"Id":"1FACAE87-AD7E-4502-B006-E39526C1C100","Nickname":"Alex Arroyo","Firstname":"Alex","Lastname":"Arroyo","City":"CO Springs","Country":"United States","ProfileImageUrl":"/Content/Account/Images/default-profile.png?637156596229260733","CanShareData":true},"FirstAscender":false,"Rating":0,"UserRating":0,"Repeats":0,"Attempts":0,"Holdsetup":{"Id":15,"Description":"MoonBoard Masters 2017","Setby":null,"DateInserted":null,"DateUpdated":null,"DateDeleted":null,"IsLocked":false,"Active":false,"Holdsets":null,"MoonBoardConfigurations":null,"HoldLayoutId":0,"AllowClimbMethods":true},"IsBenchmark":false,"IsMaster":false,"IsAssessmentProblem":false,"ProblemType":null,"Moves":[{"Id":1722659,"Description":"D5","IsStart":true,"IsEnd":false},{"Id":1722660,"Description":"F10","IsStart":false,"IsEnd":false},{"Id":1722661,"Description":"B11","IsStart":false,"IsEnd":false},{"Id":1722662,"Description":"D15","IsStart":false,"IsEnd":false},{"Id":1722663,"Description":"B16","IsStart":false,"IsEnd":false},{"Id":1722664,"Description":"B18","IsStart":false,"IsEnd":true}],"Holdsets":null,"Locations":[{"Id":0,"Holdset":null,"Description":null,"X":145,"Y":86,"Color":"0xFF0000","Rotation":0,"Type":0,"HoldNumber":null,"Direction":0,"DirectionString":"N"},{"Id":0,"Holdset":null,"Description":null,"X":145,"Y":186,"Color":"0x0000FF","Rotation":0,"Type":0,"HoldNumber":null,"Direction":0,"DirectionString":"N"},{"Id":0,"Holdset":null,"Description":null,"X":145,"Y":436,"Color":"0x0000FF","Rotation":0,"Type":0,"HoldNumber":null,"Direction":0,"DirectionString":"N"},{"Id":0,"Holdset":null,"Description":null,"X":245,"Y":236,"Color":"0x0000FF","Rotation":0,"Type":0,"HoldNumber":null,"Direction":0,"DirectionString":"N"},{"Id":0,"Holdset":null,"Description":null,"X":245,"Y":736,"Color":"0x00FF00","Rotation":0,"Type":0,"HoldNumber":null,"Direction":0,"DirectionString":"N"},{"Id":0,"Holdset":null,"Description":null,"X":345,"Y":486,"Color":"0x0000FF","Rotation":0,"Type":0,"HoldNumber":null,"Direction":0,"DirectionString":"N"}],"RepeatText":"Be the first to repeat this problem","NumberOfTries":null,"NameForUrl":"lobsta","Upgraded":false,"Downgraded":false,"Id":317929,"ApiId":0,"DateInserted":"\/Date(1522608901490)\/","DateUpdated":null,"DateDeleted":null,"DateTimeString":"01 Apr 2018 19:55"},{"Method":"Feet follow hands","Name":"BEANS AND RICE","Grade":"6C+","UserGrade":null,"MoonBoardConfiguration":{"Id":1,"Description":"40° MoonBoard","LowGrade":null,"HighGrade":null},"MoonBoardConfigurationId":0,"Setter":{"Id":"1FACAE87-AD7E-4502-B006-E39526C1C100","Nickname":"Alex Arroyo","Firstname":"Alex","Lastname":"Arroyo","City":"CO Springs","Country":"United States","ProfileImageUrl":"/Content/Account/Images/default-profile.png?637156596229416995","CanShareData":true},"FirstAscender":false,"Rating":0,"UserRating":0,"Repeats":0,"Attempts":0,"Holdsetup":{"Id":15,"Description":"MoonBoard Masters 2017","Setby":null,"DateInserted":null,"DateUpdated":null,"DateDeleted":null,"IsLocked":false,"Active":false,"Holdsets":null,"MoonBoardConfigurations":null,"HoldLayoutId":0,"AllowClimbMethods":true},"IsBenchmark":false,"IsMaster":false,"IsAssessmentProblem":false,"ProblemType":null,"Moves":[{"Id":1722653,"Description":"D3","IsStart":true,"IsEnd":false},{"Id":1722654,"Description":"I4","IsStart":true,"IsEnd":false},{"Id":1722655,"Description":"F7","IsStart":false,"IsEnd":false},{"Id":1722656,"Description":"D11","IsStart":false,"IsEnd":false},{"Id":1722657,"Description":"G14","IsStart":false,"IsEnd":false},{"Id":1722658,"Description":"F18","IsStart":false,"IsEnd":true}],"Holdsets":null,"Locations":[{"Id":0,"Holdset":null,"Description":null,"X":245,"Y":436,"Color":"0x0000FF","Rotation":0,"Type":0,"HoldNumber":null,"Direction":0,"DirectionString":"N"},{"Id":0,"Holdset":null,"Description":null,"X":245,"Y":836,"Color":"0x00FF00","Rotation":0,"Type":0,"HoldNumber":null,"Direction":0,"DirectionString":"N"},{"Id":0,"Holdset":null,"Description":null,"X":345,"Y":86,"Color":"0xFF0000","Rotation":0,"Type":0,"HoldNumber":null,"Direction":0,"DirectionString":"N"},{"Id":0,"Holdset":null,"Description":null,"X":345,"Y":636,"Color":"0x0000FF","Rotation":0,"Type":0,"HoldNumber":null,"Direction":0,"DirectionString":"N"},{"Id":0,"Holdset":null,"Description":null,"X":395,"Y":288,"Color":"0x0000FF","Rotation":0,"Type":0,"HoldNumber":null,"Direction":0,"DirectionString":"N"},{"Id":0,"Holdset":null,"Description":null,"X":495,"Y":788,"Color":"0x00FF00","Rotation":0,"Type":0,"HoldNumber":null,"Direction":0,"DirectionString":"N"}],"RepeatText":"Be the first to repeat this problem","NumberOfTries":null,"NameForUrl":"beans-and-rice","Upgraded":false,"Downgraded":false,"Id":317928,"ApiId":0,"DateInserted":"\/Date(1522608491243)\/","DateUpdated":null,"DateDeleted":null,"DateTimeString":"01 Apr 2018 19:48"},{"Method":"Feet follow hands","Name":"MIDFIELD","Grade":"6C+","UserGrade":null,"MoonBoardConfiguration":{"Id":1,"Description":"40° MoonBoard","LowGrade":null,"HighGrade":null},"MoonBoardConfigurationId":0,"Setter":{"Id":"1FACAE87-AD7E-4502-B006-E39526C1C100","Nickname":"Alex Arroyo","Firstname":"Alex","Lastname":"Arroyo","City":"CO Springs","Country":"United States","ProfileImageUrl":"/Content/Account/Images/default-profile.png?637156596229416995","CanShareData":true},"FirstAscender":false,"Rating":0,"UserRating":0,"Repeats":0,"Attempts":0,"Holdsetup":{"Id":15,"Description":"MoonBoard Masters 2017","Setby":null,"DateInserted":null,"DateUpdated":null,"DateDeleted":null,"IsLocked":false,"Active":false,"Holdsets":null,"MoonBoardConfigurations":null,"HoldLayoutId":0,"AllowClimbMethods":true},"IsBenchmark":false,"IsMaster":false,"IsAssessmentProblem":false,"ProblemType":null,"Moves":[{"Id":1722644,"Description":"J4","IsStart":true,"IsEnd":false},{"Id":1722645,"Description":"K3","IsStart":true,"IsEnd":false},{"Id":1722646,"Description":"E7","IsStart":false,"IsEnd":false},{"Id":1722647,"Description":"G9","IsStart":false,"IsEnd":false},{"Id":1722648,"Description":"E12","IsStart":false,"IsEnd":false},{"Id":1722649,"Description":"G15","IsStart":false,"IsEnd":false},{"Id":1722650,"Description":"D16","IsStart":false,"IsEnd":false},{"Id":1722651,"Description":"J18","IsStart":false,"IsEnd":true},{"Id":1722652,"Description":"I6","IsStart":false,"IsEnd":false}],"Holdsets":null,"Locations":[{"Id":0,"Holdset":null,"Description":null,"X":245,"Y":186,"Color":"0x0000FF","Rotation":0,"Type":0,"HoldNumber":null,"Direction":0,"DirectionString":"N"},{"Id":0,"Holdset":null,"Description":null,"X":295,"Y":638,"Color":"0x0000FF","Rotation":0,"Type":0,"HoldNumber":null,"Direction":0,"DirectionString":"N"},{"Id":0,"Holdset":null,"Description":null,"X":295,"Y":388,"Color":"0x0000FF","Rotation":0,"Type":0,"HoldNumber":null,"Direction":0,"DirectionString":"N"},{"Id":0,"Holdset":null,"Description":null,"X":395,"Y":538,"Color":"0x0000FF","Rotation":0,"Type":0,"HoldNumber":null,"Direction":0,"DirectionString":"N"},{"Id":0,"Holdset":null,"Description":null,"X":395,"Y":238,"Color":"0x0000FF","Rotation":0,"Type":0,"HoldNumber":null,"Direction":0,"DirectionString":"N"},{"Id":0,"Holdset":null,"Description":null,"X":495,"Y":688,"Color":"0x0000FF","Rotation":0,"Type":0,"HoldNumber":null,"Direction":0,"DirectionString":"N"},{"Id":0,"Holdset":null,"Description":null,"X":545,"Y":86,"Color":"0xFF0000","Rotation":0,"Type":0,"HoldNumber":null,"Direction":0,"DirectionString":"N"},{"Id":0,"Holdset":null,"Description":null,"X":545,"Y":786,"Color":"0x00FF00","Rotation":0,"Type":0,"HoldNumber":null,"Direction":0,"DirectionString":"N"},{"Id":0,"Holdset":null,"Description":null,"X":595,"Y":838,"Color":"0x00FF00","Rotation":0,"Type":0,"HoldNumber":null,"Direction":0,"DirectionString":"N"}],"RepeatText":"Be the first to repeat this problem","NumberOfTries":null,"NameForUrl":"midfield","Upgraded":false,"Downgraded":false,"Id":317927,"ApiId":0,"DateInserted":"\/Date(1522607784647)\/","DateUpdated":null,"DateDeleted":null,"DateTimeString":"01 Apr 2018 19:36"},{"Method":"Feet follow hands + screw ons","Name":"CAPTAIN FITZROY","Grade":"7A+","UserGrade":null,"MoonBoardConfiguration":{"Id":1,"Description":"40° MoonBoard","LowGrade":null,"HighGrade":null},"MoonBoardConfigurationId":0,"Setter":{"Id":"AEA5DC90-C288-45B5-A268-31FBBC76F56F","Nickname":"Oden Climbman","Firstname":"Oden","Lastname":"Climbman","City":"Salt Lake City","Country":"UNITED STATES ","ProfileImageUrl":"/Content/Account/Images/default-profile.png?637156596229416995","CanShareData":true},"FirstAscender":false,"Rating":0,"UserRating":3,"Repeats":1,"Attempts":0,"Holdsetup":{"Id":15,"Description":"MoonBoard Masters 2017","Setby":null,"DateInserted":null,"DateUpdated":null,"DateDeleted":null,"IsLocked":false,"Active":false,"Holdsets":null,"MoonBoardConfigurations":null,"HoldLayoutId":0,"AllowClimbMethods":true},"IsBenchmark":false,"IsMaster":false,"IsAssessmentProblem":false,"ProblemType":null,"Moves":[{"Id":1722639,"Description":"G6","IsStart":true,"IsEnd":false},{"Id":1722640,"Description":"G10","IsStart":false,"IsEnd":false},{"Id":1722641,"Description":"B12","IsStart":false,"IsEnd":false},{"Id":1722642,"Description":"E14","IsStart":false,"IsEnd":false},{"Id":1722643,"Description":"C18","IsStart":false,"IsEnd":true}],"Holdsets":null,"Locations":[{"Id":0,"Holdset":null,"Description":null,"X":145,"Y":386,"Color":"0x0000FF","Rotation":0,"Type":0,"HoldNumber":null,"Direction":0,"DirectionString":"N"},{"Id":0,"Holdset":null,"Description":null,"X":195,"Y":88,"Color":"0xFF0000","Rotation":0,"Type":0,"HoldNumber":null,"Direction":0,"DirectionString":"N"},{"Id":0,"Holdset":null,"Description":null,"X":295,"Y":288,"Color":"0x0000FF","Rotation":0,"Type":0,"HoldNumber":null,"Direction":0,"DirectionString":"N"},{"Id":0,"Holdset":null,"Description":null,"X":395,"Y":688,"Color":"0x00FF00","Rotation":0,"Type":0,"HoldNumber":null,"Direction":0,"DirectionString":"N"},{"Id":0,"Holdset":null,"Description":null,"X":395,"Y":488,"Color":"0x0000FF","Rotation":0,"Type":0,"HoldNumber":null,"Direction":0,"DirectionString":"N"}],"RepeatText":"1 climber  has repeated this problem","NumberOfTries":null,"NameForUrl":"captain-fitzroy","Upgraded":false,"Downgraded":false,"Id":317926,"ApiId":0,"DateInserted":"\/Date(1522607174737)\/","DateUpdated":null,"DateDeleted":null,"DateTimeString":"01 Apr 2018 19:26"},{"Method":"Feet follow hands","Name":"LEFTSIDE SKILLS B","Grade":"6B+","UserGrade":null,"MoonBoardConfiguration":{"Id":1,"Description":"40° MoonBoard","LowGrade":null,"HighGrade":null},"MoonBoardConfigurationId":0,"Setter":{"Id":"1FACAE87-AD7E-4502-B006-E39526C1C100","Nickname":"Alex Arroyo","Firstname":"Alex","Lastname":"Arroyo","City":"CO Springs","Country":"United States","ProfileImageUrl":"/Content/Account/Images/default-profile.png?637156596229416995","CanShareData":true},"FirstAscender":false,"Rating":0,"UserRating":3,"Repeats":3,"Attempts":0,"Holdsetup":{"Id":15,"Description":"MoonBoard Masters 2017","Setby":null,"DateInserted":null,"DateUpdated":null,"DateDeleted":null,"IsLocked":false,"Active":false,"Holdsets":null,"MoonBoardConfigurations":null,"HoldLayoutId":0,"AllowClimbMethods":true},"IsBenchmark":false,"IsMaster":false,"IsAssessmentProblem":false,"ProblemType":null,"Moves":[{"Id":1722632,"Description":"A5","IsStart":true,"IsEnd":false},{"Id":1722633,"Description":"E8","IsStart":false,"IsEnd":false},{"Id":1722634,"Description":"A11","IsStart":false,"IsEnd":false},{"Id":1722635,"Description":"D13","IsStart":false,"IsEnd":false},{"Id":1722636,"Description":"B15","IsStart":false,"IsEnd":false},{"Id":1722637,"Description":"D17","IsStart":false,"IsEnd":false},{"Id":1722638,"Description":"B18","IsStart":false,"IsEnd":true}],"Holdsets":null,"Locations":[{"Id":0,"Holdset":null,"Description":null,"X":95,"Y":738,"Color":"0x00FF00","Rotation":0,"Type":0,"HoldNumber":null,"Direction":0,"DirectionString":"N"},{"Id":0,"Holdset":null,"Description":null,"X":95,"Y":438,"Color":"0x0000FF","Rotation":0,"Type":0,"HoldNumber":null,"Direction":0,"DirectionString":"N"},{"Id":0,"Holdset":null,"Description":null,"X":145,"Y":86,"Color":"0xFF0000","Rotation":0,"Type":0,"HoldNumber":null,"Direction":0,"DirectionString":"N"},{"Id":0,"Holdset":null,"Description":null,"X":145,"Y":236,"Color":"0x0000FF","Rotation":0,"Type":0,"HoldNumber":null,"Direction":0,"DirectionString":"N"},{"Id":0,"Holdset":null,"Description":null,"X":245,"Y":136,"Color":"0x0000FF","Rotation":0,"Type":0,"HoldNumber":null,"Direction":0,"DirectionString":"N"},{"Id":0,"Holdset":null,"Description":null,"X":245,"Y":336,"Color":"0x0000FF","Rotation":0,"Type":0,"HoldNumber":null,"Direction":0,"DirectionString":"N"},{"Id":0,"Holdset":null,"Description":null,"X":295,"Y":588,"Color":"0x0000FF","Rotation":0,"Type":0,"HoldNumber":null,"Direction":0,"DirectionString":"N"}],"RepeatText":"3 climbers  have repeated this problem","NumberOfTries":null,"NameForUrl":"leftside-skills-b","Upgraded":false,"Downgraded":false,"Id":317925,"ApiId":0,"DateInserted":"\/Date(1522607103950)\/","DateUpdated":null,"DateDeleted":null,"DateTimeString":"01 Apr 2018 19:25"},{"Method":"Feet follow hands + screw ons","Name":"SMALL AND CRIMPY","Grade":"7A+","UserGrade":null,"MoonBoardConfiguration":{"Id":1,"Description":"40° MoonBoard","LowGrade":null,"HighGrade":null},"MoonBoardConfigurationId":0,"Setter":{"Id":"AEA5DC90-C288-45B5-A268-31FBBC76F56F","Nickname":"Oden Climbman","Firstname":"Oden","Lastname":"Climbman","City":"Salt Lake City","Country":"UNITED STATES ","ProfileImageUrl":"/Content/Account/Images/default-profile.png?637156596229416995","CanShareData":true},"FirstAscender":false,"Rating":0,"UserRating":0,"Repeats":0,"Attempts":0,"Holdsetup":{"Id":15,"Description":"MoonBoard Masters 2017","Setby":null,"DateInserted":null,"DateUpdated":null,"DateDeleted":null,"IsLocked":false,"Active":false,"Holdsets":null,"MoonBoardConfigurations":null,"HoldLayoutId":0,"AllowClimbMethods":true},"IsBenchmark":false,"IsMaster":false,"IsAssessmentProblem":false,"ProblemType":null,"Moves":[{"Id":1722627,"Description":"J2","IsStart":true,"IsEnd":false},{"Id":1722628,"Description":"H5","IsStart":true,"IsEnd":false},{"Id":1722629,"Description":"I7","IsStart":false,"IsEnd":false},{"Id":1722630,"Description":"E13","IsStart":false,"IsEnd":false},{"Id":1722631,"Description":"J18","IsStart":false,"IsEnd":true}],"Holdsets":null,"Locations":[{"Id":0,"Holdset":null,"Description":null,"X":295,"Y":338,"Color":"0x0000FF","Rotation":0,"Type":0,"HoldNumber":null,"Direction":0,"DirectionString":"N"},{"Id":0,"Holdset":null,"Description":null,"X":445,"Y":736,"Color":"0x00FF00","Rotation":0,"Type":0,"HoldNumber":null,"Direction":0,"DirectionString":"N"},{"Id":0,"Holdset":null,"Description":null,"X":495,"Y":638,"Color":"0x0000FF","Rotation":0,"Type":0,"HoldNumber":null,"Direction":0,"DirectionString":"N"},{"Id":0,"Holdset":null,"Description":null,"X":545,"Y":86,"Color":"0xFF0000","Rotation":0,"Type":0,"HoldNumber":null,"Direction":0,"DirectionString":"N"},{"Id":0,"Holdset":null,"Description":null,"X":545,"Y":886,"Color":"0x00FF00","Rotation":0,"Type":0,"HoldNumber":null,"Direction":0,"DirectionString":"N"}],"RepeatText":"Be the first to repeat this problem","NumberOfTries":null,"NameForUrl":"small-and-crimpy","Upgraded":false,"Downgraded":false,"Id":317924,"ApiId":0,"DateInserted":"\/Date(1522606101377)\/","DateUpdated":null,"DateDeleted":null,"DateTimeString":"01 Apr 2018 19:08"},{"Method":"Feet follow hands","Name":"A CRIMP AND A HIGHSTEP","Grade":"7C+","UserGrade":null,"MoonBoardConfiguration":{"Id":1,"Description":"40° MoonBoard","LowGrade":null,"HighGrade":null},"MoonBoardConfigurationId":0,"Setter":{"Id":"3DD67094-67F4-4E95-83B2-01D24B1A4F0F","Nickname":"Kyle Fisher","Firstname":"Kyle","Lastname":"Fisher","City":"Louisville ","Country":"UNITED STATES OF AMERICA","ProfileImageUrl":"/Content/Account/Images/default-profile.png?637156596229416995","CanShareData":true},"FirstAscender":false,"Rating":0,"UserRating":3,"Repeats":11,"Attempts":0,"Holdsetup":{"Id":15,"Description":"MoonBoard Masters 2017","Setby":null,"DateInserted":null,"DateUpdated":null,"DateDeleted":null,"IsLocked":false,"Active":false,"Holdsets":null,"MoonBoardConfigurations":null,"HoldLayoutId":0,"AllowClimbMethods":true},"IsBenchmark":false,"IsMaster":false,"IsAssessmentProblem":false,"ProblemType":null,"Moves":[{"Id":1722619,"Description":"E3","IsStart":true,"IsEnd":false},{"Id":1722620,"Description":"E4","IsStart":true,"IsEnd":false},{"Id":1722621,"Description":"H8","IsStart":false,"IsEnd":false},{"Id":1722622,"Description":"D11","IsStart":false,"IsEnd":false},{"Id":1722623,"Description":"D14","IsStart":false,"IsEnd":false},{"Id":1722624,"Description":"A9","IsStart":false,"IsEnd":false},{"Id":1722625,"Description":"B16","IsStart":false,"IsEnd":false},{"Id":1722626,"Description":"A18","IsStart":false,"IsEnd":true}],"Holdsets":null,"Locations":[{"Id":0,"Holdset":null,"Description":null,"X":95,"Y":538,"Color":"0x0000FF","Rotation":0,"Type":0,"HoldNumber":null,"Direction":0,"DirectionString":"N"},{"Id":0,"Holdset":null,"Description":null,"X":95,"Y":88,"Color":"0xFF0000","Rotation":0,"Type":0,"HoldNumber":null,"Direction":0,"DirectionString":"N"},{"Id":0,"Holdset":null,"Description":null,"X":145,"Y":186,"Color":"0x0000FF","Rotation":0,"Type":0,"HoldNumber":null,"Direction":0,"DirectionString":"N"},{"Id":0,"Holdset":null,"Description":null,"X":245,"Y":286,"Color":"0x0000FF","Rotation":0,"Type":0,"HoldNumber":null,"Direction":0,"DirectionString":"N"},{"Id":0,"Holdset":null,"Description":null,"X":245,"Y":436,"Color":"0x0000FF","Rotation":0,"Type":0,"HoldNumber":null,"Direction":0,"DirectionString":"N"},{"Id":0,"Holdset":null,"Description":null,"X":295,"Y":838,"Color":"0x00FF00","Rotation":0,"Type":0,"HoldNumber":null,"Direction":0,"DirectionString":"N"},{"Id":0,"Holdset":null,"Description":null,"X":295,"Y":788,"Color":"0x00FF00","Rotation":0,"Type":0,"HoldNumber":null,"Direction":0,"DirectionString":"N"},{"Id":0,"Holdset":null,"Description":null,"X":445,"Y":586,"Color":"0x0000FF","Rotation":0,"Type":0,"HoldNumber":null,"Direction":0,"DirectionString":"N"}],"RepeatText":"11 climbers  have repeated this problem","NumberOfTries":null,"NameForUrl":"a-crimp-and-a-highstep","Upgraded":false,"Downgraded":false,"Id":317923,"ApiId":0,"DateInserted":"\/Date(1522605981590)\/","DateUpdated":null,"DateDeleted":null,"DateTimeString":"01 Apr 2018 19:06"},{"Method":"Feet follow hands","Name":"VICARIOUS LIVING","Grade":"7B+","UserGrade":null,"MoonBoardConfiguration":{"Id":1,"Description":"40° MoonBoard","LowGrade":null,"HighGrade":null},"MoonBoardConfigurationId":0,"Setter":{"Id":"3DD67094-67F4-4E95-83B2-01D24B1A4F0F","Nickname":"Kyle Fisher","Firstname":"Kyle","Lastname":"Fisher","City":"Louisville ","Country":"UNITED STATES OF AMERICA","ProfileImageUrl":"/Content/Account/Images/default-profile.png?637156596229573258","CanShareData":true},"FirstAscender":false,"Rating":0,"UserRating":3,"Repeats":4,"Attempts":0,"Holdsetup":{"Id":15,"Description":"MoonBoard Masters 2017","Setby":null,"DateInserted":null,"DateUpdated":null,"DateDeleted":null,"IsLocked":false,"Active":false,"Holdsets":null,"MoonBoardConfigurations":null,"HoldLayoutId":0,"AllowClimbMethods":true},"IsBenchmark":false,"IsMaster":false,"IsAssessmentProblem":false,"ProblemType":null,"Moves":[{"Id":1722611,"Description":"B4","IsStart":true,"IsEnd":false},{"Id":1722612,"Description":"B8","IsStart":false,"IsEnd":false},{"Id":1722613,"Description":"H8","IsStart":false,"IsEnd":false},{"Id":1722614,"Description":"F11","IsStart":false,"IsEnd":false},{"Id":1722615,"Description":"D14","IsStart":false,"IsEnd":false},{"Id":1722616,"Description":"G16","IsStart":false,"IsEnd":false},{"Id":1722617,"Description":"G17","IsStart":false,"IsEnd":false},{"Id":1722618,"Description":"K18","IsStart":false,"IsEnd":true}],"Holdsets":null,"Locations":[{"Id":0,"Holdset":null,"Description":null,"X":145,"Y":586,"Color":"0x0000FF","Rotation":0,"Type":0,"HoldNumber":null,"Direction":0,"DirectionString":"N"},{"Id":0,"Holdset":null,"Description":null,"X":145,"Y":786,"Color":"0x00FF00","Rotation":0,"Type":0,"HoldNumber":null,"Direction":0,"DirectionString":"N"},{"Id":0,"Holdset":null,"Description":null,"X":245,"Y":286,"Color":"0x0000FF","Rotation":0,"Type":0,"HoldNumber":null,"Direction":0,"DirectionString":"N"},{"Id":0,"Holdset":null,"Description":null,"X":345,"Y":436,"Color":"0x0000FF","Rotation":0,"Type":0,"HoldNumber":null,"Direction":0,"DirectionString":"N"},{"Id":0,"Holdset":null,"Description":null,"X":395,"Y":188,"Color":"0x0000FF","Rotation":0,"Type":0,"HoldNumber":null,"Direction":0,"DirectionString":"N"},{"Id":0,"Holdset":null,"Description":null,"X":395,"Y":138,"Color":"0x0000FF","Rotation":0,"Type":0,"HoldNumber":null,"Direction":0,"DirectionString":"N"},{"Id":0,"Holdset":null,"Description":null,"X":445,"Y":586,"Color":"0x0000FF","Rotation":0,"Type":0,"HoldNumber":null,"Direction":0,"DirectionString":"N"},{"Id":0,"Holdset":null,"Description":null,"X":595,"Y":88,"Color":"0xFF0000","Rotation":0,"Type":0,"HoldNumber":null,"Direction":0,"DirectionString":"N"}],"RepeatText":"4 climbers  have repeated this problem","NumberOfTries":null,"NameForUrl":"vicarious-living","Upgraded":false,"Downgraded":false,"Id":317922,"ApiId":0,"DateInserted":"\/Date(1522605553053)\/","DateUpdated":null,"DateDeleted":null,"DateTimeString":"01 Apr 2018 18:59"},{"Method":"Feet follow hands","Name":"UNDER THE RISING SUN","Grade":"6B","UserGrade":"6B","MoonBoardConfiguration":{"Id":1,"Description":"40° MoonBoard","LowGrade":null,"HighGrade":null},"MoonBoardConfigurationId":0,"Setter":{"Id":"d01173a9-40fc-4490-8c8c-4a3606931679","Nickname":"Jaspy","Firstname":"jasper","Lastname":"Mesenbrink","City":"san Diego","Country":"USA","ProfileImageUrl":"/Content/Account/Images/default-profile.png?637156596229573258","CanShareData":true},"FirstAscender":false,"Rating":0,"UserRating":2,"Repeats":10,"Attempts":0,"Holdsetup":{"Id":15,"Description":"MoonBoard Masters 2017","Setby":null,"DateInserted":null,"DateUpdated":null,"DateDeleted":null,"IsLocked":false,"Active":false,"Holdsets":null,"MoonBoardConfigurations":null,"HoldLayoutId":0,"AllowClimbMethods":true},"IsBenchmark":false,"IsMaster":false,"IsAssessmentProblem":false,"ProblemType":null,"Moves":[{"Id":1722603,"Description":"H3","IsStart":true,"IsEnd":false},{"Id":1722604,"Description":"E4","IsStart":true,"IsEnd":false},{"Id":1722605,"Description":"G7","IsStart":false,"IsEnd":false},{"Id":1722606,"Description":"D9","IsStart":false,"IsEnd":false},{"Id":1722607,"Description":"F12","IsStart":false,"IsEnd":false},{"Id":1722608,"Description":"D15","IsStart":false,"IsEnd":false},{"Id":1722609,"Description":"D18","IsStart":false,"IsEnd":true},{"Id":1722610,"Description":"B6","IsStart":false,"IsEnd":false}],"Holdsets":null,"Locations":[{"Id":0,"Holdset":null,"Description":null,"X":145,"Y":686,"Color":"0x0000FF","Rotation":0,"Type":0,"HoldNumber":null,"Direction":0,"DirectionString":"N"},{"Id":0,"Holdset":null,"Description":null,"X":245,"Y":86,"Color":"0xFF0000","Rotation":0,"Type":0,"HoldNumber":null,"Direction":0,"DirectionString":"N"},{"Id":0,"Holdset":null,"Description":null,"X":245,"Y":236,"Color":"0x0000FF","Rotation":0,"Type":0,"HoldNumber":null,"Direction":0,"DirectionString":"N"},{"Id":0,"Holdset":null,"Description":null,"X":245,"Y":536,"Color":"0x0000FF","Rotation":0,"Type":0,"HoldNumber":null,"Direction":0,"DirectionString":"N"},{"Id":0,"Holdset":null,"Description":null,"X":295,"Y":788,"Color":"0x00FF00","Rotation":0,"Type":0,"HoldNumber":null,"Direction":0,"DirectionString":"N"},{"Id":0,"Holdset":null,"Description":null,"X":345,"Y":386,"Color":"0x0000FF","Rotation":0,"Type":0,"HoldNumber":null,"Direction":0,"DirectionString":"N"},{"Id":0,"Holdset":null,"Description":null,"X":395,"Y":638,"Color":"0x0000FF","Rotation":0,"Type":0,"HoldNumber":null,"Direction":0,"DirectionString":"N"},{"Id":0,"Holdset":null,"Description":null,"X":445,"Y":836,"Color":"0x00FF00","Rotation":0,"Type":0,"HoldNumber":null,"Direction":0,"DirectionString":"N"}],"RepeatText":"10 climbers  have repeated this problem","NumberOfTries":null,"NameForUrl":"under-the-rising-sun","Upgraded":false,"Downgraded":false,"Id":317921,"ApiId":0,"DateInserted":"\/Date(1522598793283)\/","DateUpdated":null,"DateDeleted":null,"DateTimeString":"01 Apr 2018 17:06"},{"Method":"Feet follow hands","Name":"HOW DO I DO","Grade":"6C","UserGrade":"6C","MoonBoardConfiguration":{"Id":1,"Description":"40° MoonBoard","LowGrade":null,"HighGrade":null},"MoonBoardConfigurationId":0,"Setter":{"Id":"d01173a9-40fc-4490-8c8c-4a3606931679","Nickname":"Jaspy","Firstname":"jasper","Lastname":"Mesenbrink","City":"san Diego","Country":"USA","ProfileImageUrl":"/Content/Account/Images/default-profile.png?637156596230042045","CanShareData":true},"FirstAscender":false,"Rating":0,"UserRating":2,"Repeats":59,"Attempts":0,"Holdsetup":{"Id":15,"Description":"MoonBoard Masters 2017","Setby":null,"DateInserted":null,"DateUpdated":null,"DateDeleted":null,"IsLocked":false,"Active":false,"Holdsets":null,"MoonBoardConfigurations":null,"HoldLayoutId":0,"AllowClimbMethods":true},"IsBenchmark":false,"IsMaster":false,"IsAssessmentProblem":false,"ProblemType":null,"Moves":[{"Id":1722596,"Description":"D5","IsStart":true,"IsEnd":false},{"Id":1722597,"Description":"I4","IsStart":true,"IsEnd":false},{"Id":1722598,"Description":"I8","IsStart":false,"IsEnd":false},{"Id":1722599,"Description":"D9","IsStart":false,"IsEnd":false},{"Id":1722600,"Description":"F12","IsStart":false,"IsEnd":false},{"Id":1722601,"Description":"H15","IsStart":false,"IsEnd":false},{"Id":1722602,"Description":"F18","IsStart":false,"IsEnd":true}],"Holdsets":null,"Locations":[{"Id":0,"Holdset":null,"Description":null,"X":245,"Y":536,"Color":"0x0000FF","Rotation":0,"Type":0,"HoldNumber":null,"Direction":0,"DirectionString":"N"},{"Id":0,"Holdset":null,"Description":null,"X":245,"Y":736,"Color":"0x00FF00","Rotation":0,"Type":0,"HoldNumber":null,"Direction":0,"DirectionString":"N"},{"Id":0,"Holdset":null,"Description":null,"X":345,"Y":86,"Color":"0xFF0000","Rotation":0,"Type":0,"HoldNumber":null,"Direction":0,"DirectionString":"N"},{"Id":0,"Holdset":null,"Description":null,"X":345,"Y":386,"Color":"0x0000FF","Rotation":0,"Type":0,"HoldNumber":null,"Direction":0,"DirectionString":"N"},{"Id":0,"Holdset":null,"Description":null,"X":445,"Y":236,"Color":"0x0000FF","Rotation":0,"Type":0,"HoldNumber":null,"Direction":0,"DirectionString":"N"},{"Id":0,"Holdset":null,"Description":null,"X":495,"Y":788,"Color":"0x00FF00","Rotation":0,"Type":0,"HoldNumber":null,"Direction":0,"DirectionString":"N"},{"Id":0,"Holdset":null,"Description":null,"X":495,"Y":588,"Color":"0x0000FF","Rotation":0,"Type":0,"HoldNumber":null,"Direction":0,"DirectionString":"N"}],"RepeatText":"59 climbers  have repeated this problem","NumberOfTries":null,"NameForUrl":"how-do-i-do","Upgraded":false,"Downgraded":false,"Id":317920,"ApiId":0,"DateInserted":"\/Date(1522598529507)\/","DateUpdated":null,"DateDeleted":null,"DateTimeString":"01 Apr 2018 17:02"},{"Method":"Feet follow hands","Name":"THE UGLY TRUTH","Grade":"6C","UserGrade":null,"MoonBoardConfiguration":{"Id":1,"Description":"40° MoonBoard","LowGrade":null,"HighGrade":null},"MoonBoardConfigurationId":0,"Setter":{"Id":"55C65799-AB21-496C-A34E-1CC4B3210B27","Nickname":"Kyle Knapp","Firstname":"Kyle","Lastname":"Knapp","City":"Warwick, NY","Country":"United States","ProfileImageUrl":"/Content/Account/Users/Profile/55C65799-AB21-496C-A34E-1CC4B3210B27.JPG?637156596230042045","CanShareData":true},"FirstAscender":false,"Rating":0,"UserRating":3,"Repeats":8,"Attempts":0,"Holdsetup":{"Id":15,"Description":"MoonBoard Masters 2017","Setby":null,"DateInserted":null,"DateUpdated":null,"DateDeleted":null,"IsLocked":false,"Active":false,"Holdsets":null,"MoonBoardConfigurations":null,"HoldLayoutId":0,"AllowClimbMethods":true},"IsBenchmark":false,"IsMaster":false,"IsAssessmentProblem":false,"ProblemType":null,"Moves":[{"Id":1722588,"Description":"K5","IsStart":true,"IsEnd":false},{"Id":1722589,"Description":"H1","IsStart":true,"IsEnd":false},{"Id":1722590,"Description":"G6","IsStart":false,"IsEnd":false},{"Id":1722591,"Description":"G7","IsStart":false,"IsEnd":false},{"Id":1722592,"Description":"C10","IsStart":false,"IsEnd":false},{"Id":1722593,"Description":"E14","IsStart":false,"IsEnd":false},{"Id":1722594,"Description":"A16","IsStart":false,"IsEnd":false},{"Id":1722595,"Description":"F18","IsStart":false,"IsEnd":true}],"Holdsets":null,"Locations":[{"Id":0,"Holdset":null,"Description":null,"X":95,"Y":188,"Color":"0x0000FF","Rotation":0,"Type":0,"HoldNumber":null,"Direction":0,"DirectionString":"N"},{"Id":0,"Holdset":null,"Description":null,"X":195,"Y":488,"Color":"0x0000FF","Rotation":0,"Type":0,"HoldNumber":null,"Direction":0,"DirectionString":"N"},{"Id":0,"Holdset":null,"Description":null,"X":295,"Y":288,"Color":"0x0000FF","Rotation":0,"Type":0,"HoldNumber":null,"Direction":0,"DirectionString":"N"},{"Id":0,"Holdset":null,"Description":null,"X":345,"Y":86,"Color":"0xFF0000","Rotation":0,"Type":0,"HoldNumber":null,"Direction":0,"DirectionString":"N"},{"Id":0,"Holdset":null,"Description":null,"X":395,"Y":688,"Color":"0x0000FF","Rotation":0,"Type":0,"HoldNumber":null,"Direction":0,"DirectionString":"N"},{"Id":0,"Holdset":null,"Description":null,"X":395,"Y":638,"Color":"0x0000FF","Rotation":0,"Type":0,"HoldNumber":null,"Direction":0,"DirectionString":"N"},{"Id":0,"Holdset":null,"Description":null,"X":445,"Y":936,"Color":"0x00FF00","Rotation":0,"Type":0,"HoldNumber":null,"Direction":0,"DirectionString":"N"},{"Id":0,"Holdset":null,"Description":null,"X":595,"Y":738,"Color":"0x00FF00","Rotation":0,"Type":0,"HoldNumber":null,"Direction":0,"DirectionString":"N"}],"RepeatText":"8 climbers  have repeated this problem","NumberOfTries":null,"NameForUrl":"the-ugly-truth","Upgraded":false,"Downgraded":false,"Id":317919,"ApiId":0,"DateInserted":"\/Date(1522598425503)\/","DateUpdated":null,"DateDeleted":null,"DateTimeString":"01 Apr 2018 17:00"},{"Method":"Feet follow hands","Name":"GAME. SET. MATCH.","Grade":"6C+","UserGrade":"6C+","MoonBoardConfiguration":{"Id":1,"Description":"40° MoonBoard","LowGrade":null,"HighGrade":null},"MoonBoardConfigurationId":0,"Setter":{"Id":"55C65799-AB21-496C-A34E-1CC4B3210B27","Nickname":"Kyle Knapp","Firstname":"Kyle","Lastname":"Knapp","City":"Warwick, NY","Country":"United States","ProfileImageUrl":"/Content/Account/Users/Profile/55C65799-AB21-496C-A34E-1CC4B3210B27.JPG?637156596230042045","CanShareData":true},"FirstAscender":false,"Rating":0,"UserRating":2,"Repeats":17,"Attempts":0,"Holdsetup":{"Id":15,"Description":"MoonBoard Masters 2017","Setby":null,"DateInserted":null,"DateUpdated":null,"DateDeleted":null,"IsLocked":false,"Active":false,"Holdsets":null,"MoonBoardConfigurations":null,"HoldLayoutId":0,"AllowClimbMethods":true},"IsBenchmark":false,"IsMaster":false,"IsAssessmentProblem":false,"ProblemType":null,"Moves":[{"Id":1722583,"Description":"D5","IsStart":true,"IsEnd":false},{"Id":1722584,"Description":"G10","IsStart":false,"IsEnd":false},{"Id":1722585,"Description":"G13","IsStart":false,"IsEnd":false},{"Id":1722586,"Description":"B14","IsStart":false,"IsEnd":false},{"Id":1722587,"Description":"D18","IsStart":false,"IsEnd":true}],"Holdsets":null,"Locations":[{"Id":0,"Holdset":null,"Description":null,"X":145,"Y":286,"Color":"0x0000FF","Rotation":0,"Type":0,"HoldNumber":null,"Direction":0,"DirectionString":"N"},{"Id":0,"Holdset":null,"Description":null,"X":245,"Y":86,"Color":"0xFF0000","Rotation":0,"Type":0,"HoldNumber":null,"Direction":0,"DirectionString":"N"},{"Id":0,"Holdset":null,"Description":null,"X":245,"Y":736,"Color":"0x00FF00","Rotation":0,"Type":0,"HoldNumber":null,"Direction":0,"DirectionString":"N"},{"Id":0,"Holdset":null,"Description":null,"X":395,"Y":488,"Color":"0x0000FF","Rotation":0,"Type":0,"HoldNumber":null,"Direction":0,"DirectionString":"N"},{"Id":0,"Holdset":null,"Description":null,"X":395,"Y":338,"Color":"0x0000FF","Rotation":0,"Type":0,"HoldNumber":null,"Direction":0,"DirectionString":"N"}],"RepeatText":"17 climbers  have repeated this problem","NumberOfTries":null,"NameForUrl":"game-set-match","Upgraded":false,"Downgraded":false,"Id":317918,"ApiId":0,"DateInserted":"\/Date(1522598355187)\/","DateUpdated":null,"DateDeleted":null,"DateTimeString":"01 Apr 2018 16:59"},{"Method":"Feet follow hands","Name":"UNDER THE BUS","Grade":"7A","UserGrade":null,"MoonBoardConfiguration":{"Id":1,"Description":"40° MoonBoard","LowGrade":null,"HighGrade":null},"MoonBoardConfigurationId":0,"Setter":{"Id":"4dcfba05-1c7f-4a99-865b-7e44d0562328","Nickname":"yugefeng","Firstname":"Hugo","Lastname":"Daigle","City":"Canmore","Country":"Canada","ProfileImageUrl":"/Content/Account/Images/default-profile.png?637156596230042045","CanShareData":true},"FirstAscender":false,"Rating":0,"UserRating":0,"Repeats":0,"Attempts":0,"Holdsetup":{"Id":15,"Description":"MoonBoard Masters 2017","Setby":null,"DateInserted":null,"DateUpdated":null,"DateDeleted":null,"IsLocked":false,"Active":false,"Holdsets":null,"MoonBoardConfigurations":null,"HoldLayoutId":0,"AllowClimbMethods":true},"IsBenchmark":false,"IsMaster":false,"IsAssessmentProblem":false,"ProblemType":null,"Moves":[{"Id":1722575,"Description":"C4","IsStart":true,"IsEnd":false},{"Id":1722576,"Description":"D1","IsStart":true,"IsEnd":false},{"Id":1722577,"Description":"B7","IsStart":false,"IsEnd":false},{"Id":1722578,"Description":"A9","IsStart":false,"IsEnd":false},{"Id":1722579,"Description":"E10","IsStart":false,"IsEnd":false},{"Id":1722580,"Description":"C12","IsStart":false,"IsEnd":false},{"Id":1722581,"Description":"F15","IsStart":false,"IsEnd":false},{"Id":1722582,"Description":"E18","IsStart":false,"IsEnd":true}],"Holdsets":null,"Locations":[{"Id":0,"Holdset":null,"Description":null,"X":95,"Y":538,"Color":"0x0000FF","Rotation":0,"Type":0,"HoldNumber":null,"Direction":0,"DirectionString":"N"},{"Id":0,"Holdset":null,"Description":null,"X":145,"Y":636,"Color":"0x0000FF","Rotation":0,"Type":0,"HoldNumber":null,"Direction":0,"DirectionString":"N"},{"Id":0,"Holdset":null,"Description":null,"X":195,"Y":788,"Color":"0x00FF00","Rotation":0,"Type":0,"HoldNumber":null,"Direction":0,"DirectionString":"N"},{"Id":0,"Holdset":null,"Description":null,"X":195,"Y":388,"Color":"0x0000FF","Rotation":0,"Type":0,"HoldNumber":null,"Direction":0,"DirectionString":"N"},{"Id":0,"Holdset":null,"Description":null,"X":245,"Y":936,"Color":"0x00FF00","Rotation":0,"Type":0,"HoldNumber":null,"Direction":0,"DirectionString":"N"},{"Id":0,"Holdset":null,"Description":null,"X":295,"Y":488,"Color":"0x0000FF","Rotation":0,"Type":0,"HoldNumber":null,"Direction":0,"DirectionString":"N"},{"Id":0,"Holdset":null,"Description":null,"X":295,"Y":88,"Color":"0xFF0000","Rotation":0,"Type":0,"HoldNumber":null,"Direction":0,"DirectionString":"N"},{"Id":0,"Holdset":null,"Description":null,"X":345,"Y":236,"Color":"0x0000FF","Rotation":0,"Type":0,"HoldNumber":null,"Direction":0,"DirectionString":"N"}],"RepeatText":"Be the first to repeat this problem","NumberOfTries":null,"NameForUrl":"under-the-bus","Upgraded":false,"Downgraded":false,"Id":317917,"ApiId":0,"DateInserted":"\/Date(1522598153503)\/","DateUpdated":null,"DateDeleted":null,"DateTimeString":"01 Apr 2018 16:55"},{"Method":"Feet follow hands","Name":"PHUSSY","Grade":"7A+","UserGrade":null,"MoonBoardConfiguration":{"Id":1,"Description":"40° MoonBoard","LowGrade":null,"HighGrade":null},"MoonBoardConfigurationId":0,"Setter":{"Id":"5d6a1cc0-3f3c-4035-a607-765983e13146","Nickname":"PJMOONCLIMBS","Firstname":"Paul","Lastname":"Justin","City":"Singapore","Country":"Singapore","ProfileImageUrl":"/Content/Account/Images/default-profile.png?637156596230198307","CanShareData":true},"FirstAscender":false,"Rating":0,"UserRating":1,"Repeats":1,"Attempts":0,"Holdsetup":{"Id":15,"Description":"MoonBoard Masters 2017","Setby":null,"DateInserted":null,"DateUpdated":null,"DateDeleted":null,"IsLocked":false,"Active":false,"Holdsets":null,"MoonBoardConfigurations":null,"HoldLayoutId":0,"AllowClimbMethods":true},"IsBenchmark":false,"IsMaster":false,"IsAssessmentProblem":false,"ProblemType":null,"Moves":[{"Id":1722568,"Description":"I2","IsStart":true,"IsEnd":false},{"Id":1722569,"Description":"F6","IsStart":false,"IsEnd":false},{"Id":1722570,"Description":"F10","IsStart":false,"IsEnd":false},{"Id":1722571,"Description":"H2","IsStart":true,"IsEnd":false},{"Id":1722572,"Description":"I15","IsStart":false,"IsEnd":false},{"Id":1722573,"Description":"I18","IsStart":false,"IsEnd":true},{"Id":1722574,"Description":"E13","IsStart":false,"IsEnd":false}],"Holdsets":null,"Locations":[{"Id":0,"Holdset":null,"Description":null,"X":295,"Y":338,"Color":"0x0000FF","Rotation":0,"Type":0,"HoldNumber":null,"Direction":0,"DirectionString":"N"},{"Id":0,"Holdset":null,"Description":null,"X":345,"Y":486,"Color":"0x0000FF","Rotation":0,"Type":0,"HoldNumber":null,"Direction":0,"DirectionString":"N"},{"Id":0,"Holdset":null,"Description":null,"X":345,"Y":686,"Color":"0x0000FF","Rotation":0,"Type":0,"HoldNumber":null,"Direction":0,"DirectionString":"N"},{"Id":0,"Holdset":null,"Description":null,"X":445,"Y":886,"Color":"0x00FF00","Rotation":0,"Type":0,"HoldNumber":null,"Direction":0,"DirectionString":"N"},{"Id":0,"Holdset":null,"Description":null,"X":495,"Y":888,"Color":"0x00FF00","Rotation":0,"Type":0,"HoldNumber":null,"Direction":0,"DirectionString":"N"},{"Id":0,"Holdset":null,"Description":null,"X":495,"Y":238,"Color":"0x0000FF","Rotation":0,"Type":0,"HoldNumber":null,"Direction":0,"DirectionString":"N"},{"Id":0,"Holdset":null,"Description":null,"X":495,"Y":88,"Color":"0xFF0000","Rotation":0,"Type":0,"HoldNumber":null,"Direction":0,"DirectionString":"N"}],"RepeatText":"1 climber  has repeated this problem","NumberOfTries":null,"NameForUrl":"phussy","Upgraded":false,"Downgraded":false,"Id":317916,"ApiId":0,"DateInserted":"\/Date(1522596798673)\/","DateUpdated":null,"DateDeleted":null,"DateTimeString":"01 Apr 2018 16:33"},{"Method":"Feet follow hands","Name":"JOURAKADAI","Grade":"6C","UserGrade":"6C","MoonBoardConfiguration":{"Id":1,"Description":"40° MoonBoard","LowGrade":null,"HighGrade":null},"MoonBoardConfigurationId":0,"Setter":{"Id":"b93a745a-121b-48d7-a2eb-835dfdb9e10c","Nickname":"カズマ","Firstname":"abe","Lastname":"kazuma","City":"izumo","Country":"JAPAN","ProfileImageUrl":"/Content/Account/Images/default-profile.png?637156596230198307","CanShareData":true},"FirstAscender":false,"Rating":0,"UserRating":2,"Repeats":38,"Attempts":0,"Holdsetup":{"Id":15,"Description":"MoonBoard Masters 2017","Setby":null,"DateInserted":null,"DateUpdated":null,"DateDeleted":null,"IsLocked":false,"Active":false,"Holdsets":null,"MoonBoardConfigurations":null,"HoldLayoutId":0,"AllowClimbMethods":true},"IsBenchmark":false,"IsMaster":false,"IsAssessmentProblem":false,"ProblemType":null,"Moves":[{"Id":1722521,"Description":"C4","IsStart":true,"IsEnd":false},{"Id":1722522,"Description":"A5","IsStart":true,"IsEnd":false},{"Id":1722523,"Description":"D10","IsStart":false,"IsEnd":false},{"Id":1722524,"Description":"G14","IsStart":false,"IsEnd":false},{"Id":1722525,"Description":"D1","IsStart":false,"IsEnd":false},{"Id":1722526,"Description":"E16","IsStart":false,"IsEnd":false},{"Id":1722527,"Description":"H18","IsStart":false,"IsEnd":true},{"Id":1722528,"Description":"F7","IsStart":false,"IsEnd":false}],"Holdsets":null,"Locations":[{"Id":0,"Holdset":null,"Description":null,"X":95,"Y":738,"Color":"0x00FF00","Rotation":0,"Type":0,"HoldNumber":null,"Direction":0,"DirectionString":"N"},{"Id":0,"Holdset":null,"Description":null,"X":195,"Y":788,"Color":"0x00FF00","Rotation":0,"Type":0,"HoldNumber":null,"Direction":0,"DirectionString":"N"},{"Id":0,"Holdset":null,"Description":null,"X":245,"Y":486,"Color":"0x0000FF","Rotation":0,"Type":0,"HoldNumber":null,"Direction":0,"DirectionString":"N"},{"Id":0,"Holdset":null,"Description":null,"X":245,"Y":936,"Color":"0x0000FF","Rotation":0,"Type":0,"HoldNumber":null,"Direction":0,"DirectionString":"N"},{"Id":0,"Holdset":null,"Description":null,"X":295,"Y":188,"Color":"0x0000FF","Rotation":0,"Type":0,"HoldNumber":null,"Direction":0,"DirectionString":"N"},{"Id":0,"Holdset":null,"Description":null,"X":345,"Y":636,"Color":"0x0000FF","Rotation":0,"Type":0,"HoldNumber":null,"Direction":0,"DirectionString":"N"},{"Id":0,"Holdset":null,"Description":null,"X":395,"Y":288,"Color":"0x0000FF","Rotation":0,"Type":0,"HoldNumber":null,"Direction":0,"DirectionString":"N"},{"Id":0,"Holdset":null,"Description":null,"X":445,"Y":86,"Color":"0xFF0000","Rotation":0,"Type":0,"HoldNumber":null,"Direction":0,"DirectionString":"N"}],"RepeatText":"38 climbers  have repeated this problem","NumberOfTries":null,"NameForUrl":"jourakadai","Upgraded":false,"Downgraded":false,"Id":317911,"ApiId":0,"DateInserted":"\/Date(1522573422840)\/","DateUpdated":null,"DateDeleted":null,"DateTimeString":"01 Apr 2018 10:03"}],"Total":26320,"AggregateResults":null,"Errors":null}