{"Data":[{"Method":"Feet follow hands","Name":"F_Y-2","Grade":"6B","UserGrade":null,"MoonBoardConfiguration":{"Id":1,"Description":"40° MoonBoard","LowGrade":null,"HighGrade":null},"MoonBoardConfigurationId":0,"Setter":{"Id":"ef836cd8-6f10-4206-ad7c-50c5e43a3a90","Nickname":"mcflyishe ","Firstname":"mcflyishe ","Lastname":"mcflyishe ","City":"Spb ","Country":"RUSSIA ","ProfileImageUrl":"/Content/Account/Images/default-profile.png?637156588352939291","CanShareData":true},"FirstAscender":false,"Rating":0,"UserRating":1,"Repeats":2,"Attempts":0,"Holdsetup":{"Id":15,"Description":"MoonBoard Masters 2017","Setby":null,"DateInserted":null,"DateUpdated":null,"DateDeleted":null,"IsLocked":false,"Active":false,"Holdsets":null,"MoonBoardConfigurations":null,"HoldLayoutId":0,"AllowClimbMethods":true},"IsBenchmark":false,"IsMaster":false,"IsAssessmentProblem":false,"ProblemType":null,"Moves":[{"Id":1798527,"Description":"K1","IsStart":true,"IsEnd":false},{"Id":1798528,"Description":"K18","IsStart":false,"IsEnd":true},{"Id":1798529,"Description":"I16","IsStart":false,"IsEnd":false},{"Id":1798530,"Description":"K13","IsStart":false,"IsEnd":false},{"Id":1798531,"Description":"H11","IsStart":false,"IsEnd":false},{"Id":1798532,"Description":"I8","IsStart":false,"IsEnd":false},{"Id":1798533,"Description":"K9","IsStart":false,"IsEnd":false},{"Id":1798534,"Description":"K6","IsStart":false,"IsEnd":false},{"Id":1798535,"Description":"H5","IsStart":true,"IsEnd":false}],"Holdsets":null,"Locations":[{"Id":0,"Holdset":null,"Description":null,"X":445,"Y":436,"Color":"0x0000FF","Rotation":0,"Type":0,"HoldNumber":null,"Direction":0,"DirectionString":"N"},{"Id":0,"Holdset":null,"Description":null,"X":445,"Y":736,"Color":"0x00FF00","Rotation":0,"Type":0,"HoldNumber":null,"Direction":0,"DirectionString":"N"},{"Id":0,"Holdset":null,"Description":null,"X":495,"Y":588,"Color":"0x0000FF","Rotation":0,"Type":0,"HoldNumber":null,"Direction":0,"DirectionString":"N"},{"Id":0,"Holdset":null,"Description":null,"X":495,"Y":188,"Color":"0x0000FF","Rotation":0,"Type":0,"HoldNumber":null,"Direction":0,"DirectionString":"N"},{"Id":0,"Holdset":null,"Description":null,"X":595,"Y":938,"Color":"0x00FF00","Rotation":0,"Type":0,"HoldNumber":null,"Direction":0,"DirectionString":"N"},{"Id":0,"Holdset":null,"Description":null,"X":595,"Y":688,"Color":"0x0000FF","Rotation":0,"Type":0,"HoldNumber":null,"Direction":0,"DirectionString":"N"},{"Id":0,"Holdset":null,"Description":null,"X":595,"Y":538,"Color":"0x0000FF","Rotation":0,"Type":0,"HoldNumber":null,"Direction":0,"DirectionString":"N"},{"Id":0,"Holdset":null,"Description":null,"X":595,"Y":338,"Color":"0x0000FF","Rotation":0,"Type":0,"HoldNumber":null,"Direction":0,"DirectionString":"N"},{"Id":0,"Holdset":null,"Description":null,"X":595,"Y":88,"Color":"0xFF0000","Rotation":0,"Type":0,"HoldNumber":null,"Direction":0,"DirectionString":"N"}],"RepeatText":"2 climbers  have repeated this problem","NumberOfTries":null,"NameForUrl":"f_y-2","Upgraded":false,"Downgraded":false,"Id":327424,"ApiId":0,"DateInserted":"\/Date(1538590836270)\/","DateUpdated":null,"DateDeleted":null,"DateTimeString":"03 Oct 2018 19:20"},{"Method":"Feet follow hands","Name":"VESTAS","Grade":"7B+","UserGrade":null,"MoonBoardConfiguration":{"Id":1,"Description":"40° MoonBoard","LowGrade":null,"HighGrade":null},"MoonBoardConfigurationId":0,"Setter":{"Id":"6f11e103-32cc-4005-8014-52491f9c28e5","Nickname":"bns","Firstname":"Piotr","Lastname":"Bunsch","City":"Krk","Country":"POLN","ProfileImageUrl":"/Content/Account/Images/default-profile.png?637156588352939291","CanShareData":true},"FirstAscender":false,"Rating":0,"UserRating":2,"Repeats":3,"Attempts":0,"Holdsetup":{"Id":15,"Description":"MoonBoard Masters 2017","Setby":null,"DateInserted":null,"DateUpdated":null,"DateDeleted":null,"IsLocked":false,"Active":false,"Holdsets":null,"MoonBoardConfigurations":null,"HoldLayoutId":0,"AllowClimbMethods":true},"IsBenchmark":false,"IsMaster":false,"IsAssessmentProblem":false,"ProblemType":null,"Moves":[{"Id":1798517,"Description":"B2","IsStart":true,"IsEnd":false},{"Id":1798518,"Description":"D5","IsStart":true,"IsEnd":false},{"Id":1798519,"Description":"A8","IsStart":false,"IsEnd":false},{"Id":1798520,"Description":"G8","IsStart":false,"IsEnd":false},{"Id":1798521,"Description":"E10","IsStart":false,"IsEnd":false},{"Id":1798522,"Description":"K9","IsStart":false,"IsEnd":false},{"Id":1798523,"Description":"I12","IsStart":false,"IsEnd":false},{"Id":1798524,"Description":"H14","IsStart":false,"IsEnd":false},{"Id":1798525,"Description":"I15","IsStart":false,"IsEnd":false},{"Id":1798526,"Description":"F18","IsStart":false,"IsEnd":true}],"Holdsets":null,"Locations":[{"Id":0,"Holdset":null,"Description":null,"X":95,"Y":588,"Color":"0x0000FF","Rotation":0,"Type":0,"HoldNumber":null,"Direction":0,"DirectionString":"N"},{"Id":0,"Holdset":null,"Description":null,"X":145,"Y":886,"Color":"0x00FF00","Rotation":0,"Type":0,"HoldNumber":null,"Direction":0,"DirectionString":"N"},{"Id":0,"Holdset":null,"Description":null,"X":245,"Y":736,"Color":"0x00FF00","Rotation":0,"Type":0,"HoldNumber":null,"Direction":0,"DirectionString":"N"},{"Id":0,"Holdset":null,"Description":null,"X":295,"Y":488,"Color":"0x0000FF","Rotation":0,"Type":0,"HoldNumber":null,"Direction":0,"DirectionString":"N"},{"Id":0,"Holdset":null,"Description":null,"X":345,"Y":86,"Color":"0xFF0000","Rotation":0,"Type":0,"HoldNumber":null,"Direction":0,"DirectionString":"N"},{"Id":0,"Holdset":null,"Description":null,"X":395,"Y":588,"Color":"0x0000FF","Rotation":0,"Type":0,"HoldNumber":null,"Direction":0,"DirectionString":"N"},{"Id":0,"Holdset":null,"Description":null,"X":445,"Y":286,"Color":"0x0000FF","Rotation":0,"Type":0,"HoldNumber":null,"Direction":0,"DirectionString":"N"},{"Id":0,"Holdset":null,"Description":null,"X":495,"Y":388,"Color":"0x0000FF","Rotation":0,"Type":0,"HoldNumber":null,"Direction":0,"DirectionString":"N"},{"Id":0,"Holdset":null,"Description":null,"X":495,"Y":238,"Color":"0x0000FF","Rotation":0,"Type":0,"HoldNumber":null,"Direction":0,"DirectionString":"N"},{"Id":0,"Holdset":null,"Description":null,"X":595,"Y":538,"Color":"0x0000FF","Rotation":0,"Type":0,"HoldNumber":null,"Direction":0,"DirectionString":"N"}],"RepeatText":"3 climbers  have repeated this problem","NumberOfTries":null,"NameForUrl":"vestas","Upgraded":false,"Downgraded":false,"Id":327423,"ApiId":0,"DateInserted":"\/Date(1538590648817)\/","DateUpdated":null,"DateDeleted":null,"DateTimeString":"03 Oct 2018 19:17"},{"Method":"Feet follow hands","Name":"GAMESA","Grade":"7B","UserGrade":null,"MoonBoardConfiguration":{"Id":1,"Description":"40° MoonBoard","LowGrade":null,"HighGrade":null},"MoonBoardConfigurationId":0,"Setter":{"Id":"6f11e103-32cc-4005-8014-52491f9c28e5","Nickname":"bns","Firstname":"Piotr","Lastname":"Bunsch","City":"Krk","Country":"POLN","ProfileImageUrl":"/Content/Account/Images/default-profile.png?637156588353095553","CanShareData":true},"FirstAscender":false,"Rating":0,"UserRating":3,"Repeats":1,"Attempts":0,"Holdsetup":{"Id":15,"Description":"MoonBoard Masters 2017","Setby":null,"DateInserted":null,"DateUpdated":null,"DateDeleted":null,"IsLocked":false,"Active":false,"Holdsets":null,"MoonBoardConfigurations":null,"HoldLayoutId":0,"AllowClimbMethods":true},"IsBenchmark":false,"IsMaster":false,"IsAssessmentProblem":false,"ProblemType":null,"Moves":[{"Id":1798508,"Description":"I3","IsStart":true,"IsEnd":false},{"Id":1798509,"Description":"G2","IsStart":true,"IsEnd":false},{"Id":1798510,"Description":"D8","IsStart":false,"IsEnd":false},{"Id":1798511,"Description":"D9","IsStart":false,"IsEnd":false},{"Id":1798512,"Description":"A6","IsStart":false,"IsEnd":false},{"Id":1798513,"Description":"H12","IsStart":false,"IsEnd":false},{"Id":1798514,"Description":"D12","IsStart":false,"IsEnd":false},{"Id":1798515,"Description":"F15","IsStart":false,"IsEnd":false},{"Id":1798516,"Description":"E18","IsStart":false,"IsEnd":true}],"Holdsets":null,"Locations":[{"Id":0,"Holdset":null,"Description":null,"X":95,"Y":688,"Color":"0x0000FF","Rotation":0,"Type":0,"HoldNumber":null,"Direction":0,"DirectionString":"N"},{"Id":0,"Holdset":null,"Description":null,"X":245,"Y":386,"Color":"0x0000FF","Rotation":0,"Type":0,"HoldNumber":null,"Direction":0,"DirectionString":"N"},{"Id":0,"Holdset":null,"Description":null,"X":245,"Y":536,"Color":"0x0000FF","Rotation":0,"Type":0,"HoldNumber":null,"Direction":0,"DirectionString":"N"},{"Id":0,"Holdset":null,"Description":null,"X":245,"Y":586,"Color":"0x0000FF","Rotation":0,"Type":0,"HoldNumber":null,"Direction":0,"DirectionString":"N"},{"Id":0,"Holdset":null,"Description":null,"X":295,"Y":88,"Color":"0xFF0000","Rotation":0,"Type":0,"HoldNumber":null,"Direction":0,"DirectionString":"N"},{"Id":0,"Holdset":null,"Description":null,"X":345,"Y":236,"Color":"0x0000FF","Rotation":0,"Type":0,"HoldNumber":null,"Direction":0,"DirectionString":"N"},{"Id":0,"Holdset":null,"Description":null,"X":395,"Y":888,"Color":"0x00FF00","Rotation":0,"Type":0,"HoldNumber":null,"Direction":0,"DirectionString":"N"},{"Id":0,"Holdset":null,"Description":null,"X":445,"Y":386,"Color":"0x0000FF","Rotation":0,"Type":0,"HoldNumber":null,"Direction":0,"DirectionString":"N"},{"Id":0,"Holdset":null,"Description":null,"X":495,"Y":838,"Color":"0x00FF00","Rotation":0,"Type":0,"HoldNumber":null,"Direction":0,"DirectionString":"N"}],"RepeatText":"1 climber  has repeated this problem","NumberOfTries":null,"NameForUrl":"gamesa","Upgraded":false,"Downgraded":false,"Id":327422,"ApiId":0,"DateInserted":"\/Date(1538589661477)\/","DateUpdated":null,"DateDeleted":null,"DateTimeString":"03 Oct 2018 19:01"},{"Method":"Feet follow hands","Name":"ANY GOOD ?","Grade":"6B","UserGrade":null,"MoonBoardConfiguration":{"Id":1,"Description":"40° MoonBoard","LowGrade":null,"HighGrade":null},"MoonBoardConfigurationId":0,"Setter":{"Id":"7BA209D1-6C71-46D2-A995-E7FD2C382AC9","Nickname":"Elliot Marshall","Firstname":"Elliot","Lastname":"Marshall","City":"Leeds","Country":"UK","ProfileImageUrl":"/Content/Account/Images/default-profile.png?637156588353095553","CanShareData":true},"FirstAscender":false,"Rating":0,"UserRating":2,"Repeats":1,"Attempts":0,"Holdsetup":{"Id":15,"Description":"MoonBoard Masters 2017","Setby":null,"DateInserted":null,"DateUpdated":null,"DateDeleted":null,"IsLocked":false,"Active":false,"Holdsets":null,"MoonBoardConfigurations":null,"HoldLayoutId":0,"AllowClimbMethods":true},"IsBenchmark":false,"IsMaster":false,"IsAssessmentProblem":false,"ProblemType":null,"Moves":[{"Id":1798502,"Description":"E3","IsStart":true,"IsEnd":false},{"Id":1798503,"Description":"F5","IsStart":true,"IsEnd":false},{"Id":1798504,"Description":"D9","IsStart":false,"IsEnd":false},{"Id":1798505,"Description":"F13","IsStart":false,"IsEnd":false},{"Id":1798506,"Description":"I16","IsStart":false,"IsEnd":false},{"Id":1798507,"Description":"F18","IsStart":false,"IsEnd":true}],"Holdsets":null,"Locations":[{"Id":0,"Holdset":null,"Description":null,"X":245,"Y":536,"Color":"0x0000FF","Rotation":0,"Type":0,"HoldNumber":null,"Direction":0,"DirectionString":"N"},{"Id":0,"Holdset":null,"Description":null,"X":295,"Y":838,"Color":"0x00FF00","Rotation":0,"Type":0,"HoldNumber":null,"Direction":0,"DirectionString":"N"},{"Id":0,"Holdset":null,"Description":null,"X":345,"Y":86,"Color":"0xFF0000","Rotation":0,"Type":0,"HoldNumber":null,"Direction":0,"DirectionString":"N"},{"Id":0,"Holdset":null,"Description":null,"X":345,"Y":336,"Color":"0x0000FF","Rotation":0,"Type":0,"HoldNumber":null,"Direction":0,"DirectionString":"N"},{"Id":0,"Holdset":null,"Description":null,"X":345,"Y":736,"Color":"0x00FF00","Rotation":0,"Type":0,"HoldNumber":null,"Direction":0,"DirectionString":"N"},{"Id":0,"Holdset":null,"Description":null,"X":495,"Y":188,"Color":"0x0000FF","Rotation":0,"Type":0,"HoldNumber":null,"Direction":0,"DirectionString":"N"}],"RepeatText":"1 climber  has repeated this problem","NumberOfTries":null,"NameForUrl":"any-good","Upgraded":false,"Downgraded":false,"Id":327421,"ApiId":0,"DateInserted":"\/Date(1538588862207)\/","DateUpdated":null,"DateDeleted":null,"DateTimeString":"03 Oct 2018 18:47"},{"Method":"Feet follow hands","Name":"SIEMENS","Grade":"7A","UserGrade":"6C+","MoonBoardConfiguration":{"Id":1,"Description":"40° MoonBoard","LowGrade":null,"HighGrade":null},"MoonBoardConfigurationId":0,"Setter":{"Id":"6f11e103-32cc-4005-8014-52491f9c28e5","Nickname":"bns","Firstname":"Piotr","Lastname":"Bunsch","City":"Krk","Country":"POLN","ProfileImageUrl":"/Content/Account/Images/default-profile.png?637156588353095553","CanShareData":true},"FirstAscender":false,"Rating":0,"UserRating":2,"Repeats":18,"Attempts":0,"Holdsetup":{"Id":15,"Description":"MoonBoard Masters 2017","Setby":null,"DateInserted":null,"DateUpdated":null,"DateDeleted":null,"IsLocked":false,"Active":false,"Holdsets":null,"MoonBoardConfigurations":null,"HoldLayoutId":0,"AllowClimbMethods":true},"IsBenchmark":false,"IsMaster":false,"IsAssessmentProblem":false,"ProblemType":null,"Moves":[{"Id":1798496,"Description":"F5","IsStart":true,"IsEnd":false},{"Id":1798497,"Description":"D9","IsStart":false,"IsEnd":false},{"Id":1798498,"Description":"G13","IsStart":false,"IsEnd":false},{"Id":1798499,"Description":"B14","IsStart":false,"IsEnd":false},{"Id":1798500,"Description":"D17","IsStart":false,"IsEnd":false},{"Id":1798501,"Description":"D18","IsStart":false,"IsEnd":true}],"Holdsets":null,"Locations":[{"Id":0,"Holdset":null,"Description":null,"X":145,"Y":286,"Color":"0x0000FF","Rotation":0,"Type":0,"HoldNumber":null,"Direction":0,"DirectionString":"N"},{"Id":0,"Holdset":null,"Description":null,"X":245,"Y":86,"Color":"0xFF0000","Rotation":0,"Type":0,"HoldNumber":null,"Direction":0,"DirectionString":"N"},{"Id":0,"Holdset":null,"Description":null,"X":245,"Y":136,"Color":"0x0000FF","Rotation":0,"Type":0,"HoldNumber":null,"Direction":0,"DirectionString":"N"},{"Id":0,"Holdset":null,"Description":null,"X":245,"Y":536,"Color":"0x0000FF","Rotation":0,"Type":0,"HoldNumber":null,"Direction":0,"DirectionString":"N"},{"Id":0,"Holdset":null,"Description":null,"X":345,"Y":736,"Color":"0x00FF00","Rotation":0,"Type":0,"HoldNumber":null,"Direction":0,"DirectionString":"N"},{"Id":0,"Holdset":null,"Description":null,"X":395,"Y":338,"Color":"0x0000FF","Rotation":0,"Type":0,"HoldNumber":null,"Direction":0,"DirectionString":"N"}],"RepeatText":"18 climbers  have repeated this problem","NumberOfTries":null,"NameForUrl":"siemens","Upgraded":false,"Downgraded":false,"Id":327420,"ApiId":0,"DateInserted":"\/Date(1538588486553)\/","DateUpdated":null,"DateDeleted":null,"DateTimeString":"03 Oct 2018 18:41"},{"Method":"Feet follow hands","Name":"ENERCON","Grade":"7B","UserGrade":null,"MoonBoardConfiguration":{"Id":1,"Description":"40° MoonBoard","LowGrade":null,"HighGrade":null},"MoonBoardConfigurationId":0,"Setter":{"Id":"6f11e103-32cc-4005-8014-52491f9c28e5","Nickname":"bns","Firstname":"Piotr","Lastname":"Bunsch","City":"Krk","Country":"POLN","ProfileImageUrl":"/Content/Account/Images/default-profile.png?637156588353251815","CanShareData":true},"FirstAscender":false,"Rating":0,"UserRating":2,"Repeats":8,"Attempts":0,"Holdsetup":{"Id":15,"Description":"MoonBoard Masters 2017","Setby":null,"DateInserted":null,"DateUpdated":null,"DateDeleted":null,"IsLocked":false,"Active":false,"Holdsets":null,"MoonBoardConfigurations":null,"HoldLayoutId":0,"AllowClimbMethods":true},"IsBenchmark":false,"IsMaster":false,"IsAssessmentProblem":false,"ProblemType":null,"Moves":[{"Id":1798487,"Description":"A3","IsStart":true,"IsEnd":false},{"Id":1798488,"Description":"B4","IsStart":true,"IsEnd":false},{"Id":1798489,"Description":"C7","IsStart":false,"IsEnd":false},{"Id":1798490,"Description":"H9","IsStart":false,"IsEnd":false},{"Id":1798491,"Description":"H11","IsStart":false,"IsEnd":false},{"Id":1798492,"Description":"J13","IsStart":false,"IsEnd":false},{"Id":1798493,"Description":"E14","IsStart":false,"IsEnd":false},{"Id":1798494,"Description":"E17","IsStart":false,"IsEnd":false},{"Id":1798495,"Description":"B18","IsStart":false,"IsEnd":true}],"Holdsets":null,"Locations":[{"Id":0,"Holdset":null,"Description":null,"X":95,"Y":838,"Color":"0x00FF00","Rotation":0,"Type":0,"HoldNumber":null,"Direction":0,"DirectionString":"N"},{"Id":0,"Holdset":null,"Description":null,"X":145,"Y":86,"Color":"0xFF0000","Rotation":0,"Type":0,"HoldNumber":null,"Direction":0,"DirectionString":"N"},{"Id":0,"Holdset":null,"Description":null,"X":145,"Y":786,"Color":"0x00FF00","Rotation":0,"Type":0,"HoldNumber":null,"Direction":0,"DirectionString":"N"},{"Id":0,"Holdset":null,"Description":null,"X":195,"Y":638,"Color":"0x0000FF","Rotation":0,"Type":0,"HoldNumber":null,"Direction":0,"DirectionString":"N"},{"Id":0,"Holdset":null,"Description":null,"X":295,"Y":288,"Color":"0x0000FF","Rotation":0,"Type":0,"HoldNumber":null,"Direction":0,"DirectionString":"N"},{"Id":0,"Holdset":null,"Description":null,"X":295,"Y":138,"Color":"0x0000FF","Rotation":0,"Type":0,"HoldNumber":null,"Direction":0,"DirectionString":"N"},{"Id":0,"Holdset":null,"Description":null,"X":445,"Y":436,"Color":"0x0000FF","Rotation":0,"Type":0,"HoldNumber":null,"Direction":0,"DirectionString":"N"},{"Id":0,"Holdset":null,"Description":null,"X":445,"Y":536,"Color":"0x0000FF","Rotation":0,"Type":0,"HoldNumber":null,"Direction":0,"DirectionString":"N"},{"Id":0,"Holdset":null,"Description":null,"X":545,"Y":336,"Color":"0x0000FF","Rotation":0,"Type":0,"HoldNumber":null,"Direction":0,"DirectionString":"N"}],"RepeatText":"8 climbers  have repeated this problem","NumberOfTries":null,"NameForUrl":"enercon","Upgraded":false,"Downgraded":false,"Id":327419,"ApiId":0,"DateInserted":"\/Date(1538588439270)\/","DateUpdated":null,"DateDeleted":null,"DateTimeString":"03 Oct 2018 18:40"},{"Method":"Feet follow hands","Name":"RUSTY","Grade":"6C+","UserGrade":"6C+","MoonBoardConfiguration":{"Id":1,"Description":"40° MoonBoard","LowGrade":null,"HighGrade":null},"MoonBoardConfigurationId":0,"Setter":{"Id":"46A21D70-B941-43EC-9004-035DD5D94527","Nickname":"Johannes Grannes","Firstname":"Johannes","Lastname":"Grannes","City":"Oslo","Country":"NORWAY","ProfileImageUrl":"/Content/Account/Images/default-profile.png?637156588353251815","CanShareData":true},"FirstAscender":false,"Rating":0,"UserRating":2,"Repeats":10,"Attempts":0,"Holdsetup":{"Id":15,"Description":"MoonBoard Masters 2017","Setby":null,"DateInserted":null,"DateUpdated":null,"DateDeleted":null,"IsLocked":false,"Active":false,"Holdsets":null,"MoonBoardConfigurations":null,"HoldLayoutId":0,"AllowClimbMethods":true},"IsBenchmark":false,"IsMaster":false,"IsAssessmentProblem":false,"ProblemType":null,"Moves":[{"Id":1798481,"Description":"D4","IsStart":true,"IsEnd":false},{"Id":1798482,"Description":"F6","IsStart":true,"IsEnd":false},{"Id":1798483,"Description":"I8","IsStart":false,"IsEnd":false},{"Id":1798484,"Description":"E10","IsStart":false,"IsEnd":false},{"Id":1798485,"Description":"G13","IsStart":false,"IsEnd":false},{"Id":1798486,"Description":"H18","IsStart":false,"IsEnd":true}],"Holdsets":null,"Locations":[{"Id":0,"Holdset":null,"Description":null,"X":245,"Y":786,"Color":"0x00FF00","Rotation":0,"Type":0,"HoldNumber":null,"Direction":0,"DirectionString":"N"},{"Id":0,"Holdset":null,"Description":null,"X":295,"Y":488,"Color":"0x0000FF","Rotation":0,"Type":0,"HoldNumber":null,"Direction":0,"DirectionString":"N"},{"Id":0,"Holdset":null,"Description":null,"X":345,"Y":686,"Color":"0x00FF00","Rotation":0,"Type":0,"HoldNumber":null,"Direction":0,"DirectionString":"N"},{"Id":0,"Holdset":null,"Description":null,"X":395,"Y":338,"Color":"0x0000FF","Rotation":0,"Type":0,"HoldNumber":null,"Direction":0,"DirectionString":"N"},{"Id":0,"Holdset":null,"Description":null,"X":445,"Y":86,"Color":"0xFF0000","Rotation":0,"Type":0,"HoldNumber":null,"Direction":0,"DirectionString":"N"},{"Id":0,"Holdset":null,"Description":null,"X":495,"Y":588,"Color":"0x0000FF","Rotation":0,"Type":0,"HoldNumber":null,"Direction":0,"DirectionString":"N"}],"RepeatText":"10 climbers  have repeated this problem","NumberOfTries":null,"NameForUrl":"rusty","Upgraded":false,"Downgraded":false,"Id":327418,"ApiId":0,"DateInserted":"\/Date(1538587674037)\/","DateUpdated":null,"DateDeleted":null,"DateTimeString":"03 Oct 2018 18:27"},{"Method":"Feet follow hands","Name":"EASY WHALE","Grade":"6A+","UserGrade":"6A+","MoonBoardConfiguration":{"Id":1,"Description":"40° MoonBoard","LowGrade":null,"HighGrade":null},"MoonBoardConfigurationId":0,"Setter":{"Id":"386f9d07-7ecc-4add-ba0b-08ae8aed532c","Nickname":"Narrentanz","Firstname":"Matthias","Lastname":"St","City":"Flawil","Country":"Switzerland","ProfileImageUrl":"/Content/Account/Images/default-profile.png?637156588353408078","CanShareData":true},"FirstAscender":false,"Rating":0,"UserRating":2,"Repeats":27,"Attempts":0,"Holdsetup":{"Id":15,"Description":"MoonBoard Masters 2017","Setby":null,"DateInserted":null,"DateUpdated":null,"DateDeleted":null,"IsLocked":false,"Active":false,"Holdsets":null,"MoonBoardConfigurations":null,"HoldLayoutId":0,"AllowClimbMethods":true},"IsBenchmark":false,"IsMaster":false,"IsAssessmentProblem":false,"ProblemType":null,"Moves":[{"Id":1798462,"Description":"D4","IsStart":true,"IsEnd":false},{"Id":1798463,"Description":"H5","IsStart":true,"IsEnd":false},{"Id":1798464,"Description":"F7","IsStart":false,"IsEnd":false},{"Id":1798465,"Description":"I7","IsStart":false,"IsEnd":false},{"Id":1798466,"Description":"H10","IsStart":false,"IsEnd":false},{"Id":1798467,"Description":"J11","IsStart":false,"IsEnd":false},{"Id":1798468,"Description":"E16","IsStart":false,"IsEnd":false},{"Id":1798469,"Description":"F18","IsStart":false,"IsEnd":true},{"Id":1798470,"Description":"E13","IsStart":false,"IsEnd":false},{"Id":1798471,"Description":"G13","IsStart":false,"IsEnd":false}],"Holdsets":null,"Locations":[{"Id":0,"Holdset":null,"Description":null,"X":245,"Y":786,"Color":"0x00FF00","Rotation":0,"Type":0,"HoldNumber":null,"Direction":0,"DirectionString":"N"},{"Id":0,"Holdset":null,"Description":null,"X":295,"Y":338,"Color":"0x0000FF","Rotation":0,"Type":0,"HoldNumber":null,"Direction":0,"DirectionString":"N"},{"Id":0,"Holdset":null,"Description":null,"X":295,"Y":188,"Color":"0x0000FF","Rotation":0,"Type":0,"HoldNumber":null,"Direction":0,"DirectionString":"N"},{"Id":0,"Holdset":null,"Description":null,"X":345,"Y":86,"Color":"0xFF0000","Rotation":0,"Type":0,"HoldNumber":null,"Direction":0,"DirectionString":"N"},{"Id":0,"Holdset":null,"Description":null,"X":345,"Y":636,"Color":"0x0000FF","Rotation":0,"Type":0,"HoldNumber":null,"Direction":0,"DirectionString":"N"},{"Id":0,"Holdset":null,"Description":null,"X":395,"Y":338,"Color":"0x0000FF","Rotation":0,"Type":0,"HoldNumber":null,"Direction":0,"DirectionString":"N"},{"Id":0,"Holdset":null,"Description":null,"X":445,"Y":486,"Color":"0x0000FF","Rotation":0,"Type":0,"HoldNumber":null,"Direction":0,"DirectionString":"N"},{"Id":0,"Holdset":null,"Description":null,"X":445,"Y":736,"Color":"0x00FF00","Rotation":0,"Type":0,"HoldNumber":null,"Direction":0,"DirectionString":"N"},{"Id":0,"Holdset":null,"Description":null,"X":495,"Y":638,"Color":"0x0000FF","Rotation":0,"Type":0,"HoldNumber":null,"Direction":0,"DirectionString":"N"},{"Id":0,"Holdset":null,"Description":null,"X":545,"Y":436,"Color":"0x0000FF","Rotation":0,"Type":0,"HoldNumber":null,"Direction":0,"DirectionString":"N"}],"RepeatText":"27 climbers  have repeated this problem","NumberOfTries":null,"NameForUrl":"easy-whale","Upgraded":false,"Downgraded":false,"Id":327416,"ApiId":0,"DateInserted":"\/Date(1538585057067)\/","DateUpdated":null,"DateDeleted":null,"DateTimeString":"03 Oct 2018 17:44"},{"Method":"Feet follow hands + screw ons","Name":"1. WHALE-BOULDER","Grade":"6B","UserGrade":"6B","MoonBoardConfiguration":{"Id":1,"Description":"40° MoonBoard","LowGrade":null,"HighGrade":null},"MoonBoardConfigurationId":0,"Setter":{"Id":"386f9d07-7ecc-4add-ba0b-08ae8aed532c","Nickname":"Narrentanz","Firstname":"Matthias","Lastname":"St","City":"Flawil","Country":"Switzerland","ProfileImageUrl":"/Content/Account/Images/default-profile.png?637156588353564340","CanShareData":true},"FirstAscender":false,"Rating":0,"UserRating":2,"Repeats":14,"Attempts":0,"Holdsetup":{"Id":15,"Description":"MoonBoard Masters 2017","Setby":null,"DateInserted":null,"DateUpdated":null,"DateDeleted":null,"IsLocked":false,"Active":false,"Holdsets":null,"MoonBoardConfigurations":null,"HoldLayoutId":0,"AllowClimbMethods":true},"IsBenchmark":false,"IsMaster":false,"IsAssessmentProblem":false,"ProblemType":null,"Moves":[{"Id":1798454,"Description":"H5","IsStart":true,"IsEnd":false},{"Id":1798455,"Description":"D9","IsStart":false,"IsEnd":false},{"Id":1798456,"Description":"H10","IsStart":false,"IsEnd":false},{"Id":1798457,"Description":"G13","IsStart":false,"IsEnd":false},{"Id":1798458,"Description":"H18","IsStart":false,"IsEnd":true},{"Id":1798459,"Description":"E3","IsStart":true,"IsEnd":false},{"Id":1798460,"Description":"J16","IsStart":false,"IsEnd":false},{"Id":1798461,"Description":"F7","IsStart":false,"IsEnd":false}],"Holdsets":null,"Locations":[{"Id":0,"Holdset":null,"Description":null,"X":245,"Y":536,"Color":"0x0000FF","Rotation":0,"Type":0,"HoldNumber":null,"Direction":0,"DirectionString":"N"},{"Id":0,"Holdset":null,"Description":null,"X":295,"Y":838,"Color":"0x00FF00","Rotation":0,"Type":0,"HoldNumber":null,"Direction":0,"DirectionString":"N"},{"Id":0,"Holdset":null,"Description":null,"X":345,"Y":636,"Color":"0x0000FF","Rotation":0,"Type":0,"HoldNumber":null,"Direction":0,"DirectionString":"N"},{"Id":0,"Holdset":null,"Description":null,"X":395,"Y":338,"Color":"0x0000FF","Rotation":0,"Type":0,"HoldNumber":null,"Direction":0,"DirectionString":"N"},{"Id":0,"Holdset":null,"Description":null,"X":445,"Y":86,"Color":"0xFF0000","Rotation":0,"Type":0,"HoldNumber":null,"Direction":0,"DirectionString":"N"},{"Id":0,"Holdset":null,"Description":null,"X":445,"Y":486,"Color":"0x0000FF","Rotation":0,"Type":0,"HoldNumber":null,"Direction":0,"DirectionString":"N"},{"Id":0,"Holdset":null,"Description":null,"X":445,"Y":736,"Color":"0x00FF00","Rotation":0,"Type":0,"HoldNumber":null,"Direction":0,"DirectionString":"N"},{"Id":0,"Holdset":null,"Description":null,"X":545,"Y":186,"Color":"0x0000FF","Rotation":0,"Type":0,"HoldNumber":null,"Direction":0,"DirectionString":"N"}],"RepeatText":"14 climbers  have repeated this problem","NumberOfTries":null,"NameForUrl":"1-whale-boulder","Upgraded":false,"Downgraded":false,"Id":327415,"ApiId":0,"DateInserted":"\/Date(1538584511437)\/","DateUpdated":null,"DateDeleted":null,"DateTimeString":"03 Oct 2018 17:35"},{"Method":"Feet follow hands + screw ons","Name":"JEPP","Grade":"7A","UserGrade":null,"MoonBoardConfiguration":{"Id":1,"Description":"40° MoonBoard","LowGrade":null,"HighGrade":null},"MoonBoardConfigurationId":0,"Setter":{"Id":"69ec4ff4-6ca0-4bbe-be3d-538399458bc1","Nickname":"Jan Keuchel","Firstname":"Jan","Lastname":"Keuchel","City":"Bammental","Country":"Germany","ProfileImageUrl":"/Content/Account/Images/default-profile.png?637156588353564340","CanShareData":true},"FirstAscender":false,"Rating":0,"UserRating":0,"Repeats":0,"Attempts":0,"Holdsetup":{"Id":15,"Description":"MoonBoard Masters 2017","Setby":null,"DateInserted":null,"DateUpdated":null,"DateDeleted":null,"IsLocked":false,"Active":false,"Holdsets":null,"MoonBoardConfigurations":null,"HoldLayoutId":0,"AllowClimbMethods":true},"IsBenchmark":false,"IsMaster":false,"IsAssessmentProblem":false,"ProblemType":null,"Moves":[{"Id":1798445,"Description":"D2","IsStart":true,"IsEnd":false},{"Id":1798446,"Description":"D4","IsStart":true,"IsEnd":false},{"Id":1798447,"Description":"D8","IsStart":false,"IsEnd":false},{"Id":1798448,"Description":"I10","IsStart":false,"IsEnd":false},{"Id":1798449,"Description":"D14","IsStart":false,"IsEnd":false},{"Id":1798450,"Description":"I15","IsStart":false,"IsEnd":false},{"Id":1798451,"Description":"F9","IsStart":false,"IsEnd":false},{"Id":1798452,"Description":"F15","IsStart":false,"IsEnd":false},{"Id":1798453,"Description":"J18","IsStart":false,"IsEnd":true}],"Holdsets":null,"Locations":[{"Id":0,"Holdset":null,"Description":null,"X":245,"Y":286,"Color":"0x0000FF","Rotation":0,"Type":0,"HoldNumber":null,"Direction":0,"DirectionString":"N"},{"Id":0,"Holdset":null,"Description":null,"X":245,"Y":586,"Color":"0x0000FF","Rotation":0,"Type":0,"HoldNumber":null,"Direction":0,"DirectionString":"N"},{"Id":0,"Holdset":null,"Description":null,"X":245,"Y":786,"Color":"0x00FF00","Rotation":0,"Type":0,"HoldNumber":null,"Direction":0,"DirectionString":"N"},{"Id":0,"Holdset":null,"Description":null,"X":245,"Y":886,"Color":"0x00FF00","Rotation":0,"Type":0,"HoldNumber":null,"Direction":0,"DirectionString":"N"},{"Id":0,"Holdset":null,"Description":null,"X":345,"Y":236,"Color":"0x0000FF","Rotation":0,"Type":0,"HoldNumber":null,"Direction":0,"DirectionString":"N"},{"Id":0,"Holdset":null,"Description":null,"X":345,"Y":536,"Color":"0x0000FF","Rotation":0,"Type":0,"HoldNumber":null,"Direction":0,"DirectionString":"N"},{"Id":0,"Holdset":null,"Description":null,"X":495,"Y":488,"Color":"0x0000FF","Rotation":0,"Type":0,"HoldNumber":null,"Direction":0,"DirectionString":"N"},{"Id":0,"Holdset":null,"Description":null,"X":495,"Y":238,"Color":"0x0000FF","Rotation":0,"Type":0,"HoldNumber":null,"Direction":0,"DirectionString":"N"},{"Id":0,"Holdset":null,"Description":null,"X":545,"Y":86,"Color":"0xFF0000","Rotation":0,"Type":0,"HoldNumber":null,"Direction":0,"DirectionString":"N"}],"RepeatText":"Be the first to repeat this problem","NumberOfTries":null,"NameForUrl":"jepp","Upgraded":false,"Downgraded":false,"Id":327414,"ApiId":0,"DateInserted":"\/Date(1538584108243)\/","DateUpdated":null,"DateDeleted":null,"DateTimeString":"03 Oct 2018 17:28"},{"Method":"Feet follow hands","Name":"100PRRSNT","Grade":"7B","UserGrade":null,"MoonBoardConfiguration":{"Id":1,"Description":"40° MoonBoard","LowGrade":null,"HighGrade":null},"MoonBoardConfigurationId":0,"Setter":{"Id":"39DCC3FD-0F94-4D3A-93A6-5F471A5EF0F4","Nickname":"Jon Pål Hamre","Firstname":"Jon Pål","Lastname":"Hamre","City":"Oslo","Country":"NORWAY","ProfileImageUrl":"/Content/Account/Images/default-profile.png?637156588353564340","CanShareData":true},"FirstAscender":false,"Rating":0,"UserRating":0,"Repeats":0,"Attempts":0,"Holdsetup":{"Id":15,"Description":"MoonBoard Masters 2017","Setby":null,"DateInserted":null,"DateUpdated":null,"DateDeleted":null,"IsLocked":false,"Active":false,"Holdsets":null,"MoonBoardConfigurations":null,"HoldLayoutId":0,"AllowClimbMethods":true},"IsBenchmark":false,"IsMaster":false,"IsAssessmentProblem":false,"ProblemType":null,"Moves":[{"Id":1798418,"Description":"E3","IsStart":true,"IsEnd":false},{"Id":1798419,"Description":"C6","IsStart":true,"IsEnd":false},{"Id":1798420,"Description":"F10","IsStart":false,"IsEnd":false},{"Id":1798421,"Description":"E12","IsStart":false,"IsEnd":false},{"Id":1798422,"Description":"K13","IsStart":false,"IsEnd":false},{"Id":1798423,"Description":"I17","IsStart":false,"IsEnd":false},{"Id":1798424,"Description":"I18","IsStart":false,"IsEnd":true}],"Holdsets":null,"Locations":[{"Id":0,"Holdset":null,"Description":null,"X":195,"Y":688,"Color":"0x00FF00","Rotation":0,"Type":0,"HoldNumber":null,"Direction":0,"DirectionString":"N"},{"Id":0,"Holdset":null,"Description":null,"X":295,"Y":838,"Color":"0x00FF00","Rotation":0,"Type":0,"HoldNumber":null,"Direction":0,"DirectionString":"N"},{"Id":0,"Holdset":null,"Description":null,"X":295,"Y":388,"Color":"0x0000FF","Rotation":0,"Type":0,"HoldNumber":null,"Direction":0,"DirectionString":"N"},{"Id":0,"Holdset":null,"Description":null,"X":345,"Y":486,"Color":"0x0000FF","Rotation":0,"Type":0,"HoldNumber":null,"Direction":0,"DirectionString":"N"},{"Id":0,"Holdset":null,"Description":null,"X":495,"Y":138,"Color":"0x0000FF","Rotation":0,"Type":0,"HoldNumber":null,"Direction":0,"DirectionString":"N"},{"Id":0,"Holdset":null,"Description":null,"X":495,"Y":88,"Color":"0xFF0000","Rotation":0,"Type":0,"HoldNumber":null,"Direction":0,"DirectionString":"N"},{"Id":0,"Holdset":null,"Description":null,"X":595,"Y":338,"Color":"0x0000FF","Rotation":0,"Type":0,"HoldNumber":null,"Direction":0,"DirectionString":"N"}],"RepeatText":"Be the first to repeat this problem","NumberOfTries":null,"NameForUrl":"100prrsnt","Upgraded":false,"Downgraded":false,"Id":327410,"ApiId":0,"DateInserted":"\/Date(1538579952207)\/","DateUpdated":null,"DateDeleted":null,"DateTimeString":"03 Oct 2018 16:19"},{"Method":"Feet follow hands","Name":"ML ELON MUSK","Grade":"6B+","UserGrade":"6B+","MoonBoardConfiguration":{"Id":1,"Description":"40° MoonBoard","LowGrade":null,"HighGrade":null},"MoonBoardConfigurationId":0,"Setter":{"Id":"39DCC3FD-0F94-4D3A-93A6-5F471A5EF0F4","Nickname":"Jon Pål Hamre","Firstname":"Jon Pål","Lastname":"Hamre","City":"Oslo","Country":"NORWAY","ProfileImageUrl":"/Content/Account/Images/default-profile.png?637156588353564340","CanShareData":true},"FirstAscender":false,"Rating":0,"UserRating":2,"Repeats":20,"Attempts":0,"Holdsetup":{"Id":15,"Description":"MoonBoard Masters 2017","Setby":null,"DateInserted":null,"DateUpdated":null,"DateDeleted":null,"IsLocked":false,"Active":false,"Holdsets":null,"MoonBoardConfigurations":null,"HoldLayoutId":0,"AllowClimbMethods":true},"IsBenchmark":false,"IsMaster":false,"IsAssessmentProblem":false,"ProblemType":null,"Moves":[{"Id":1798407,"Description":"E3","IsStart":true,"IsEnd":false},{"Id":1798408,"Description":"B3","IsStart":true,"IsEnd":false},{"Id":1798409,"Description":"C7","IsStart":false,"IsEnd":false},{"Id":1798410,"Description":"I8","IsStart":false,"IsEnd":false},{"Id":1798411,"Description":"H10","IsStart":false,"IsEnd":false},{"Id":1798412,"Description":"J11","IsStart":false,"IsEnd":false},{"Id":1798413,"Description":"G14","IsStart":false,"IsEnd":false},{"Id":1798414,"Description":"J16","IsStart":false,"IsEnd":false},{"Id":1798415,"Description":"H18","IsStart":false,"IsEnd":true},{"Id":1798416,"Description":"J18","IsStart":false,"IsEnd":true},{"Id":1798417,"Description":"H5","IsStart":false,"IsEnd":false}],"Holdsets":null,"Locations":[{"Id":0,"Holdset":null,"Description":null,"X":145,"Y":836,"Color":"0x00FF00","Rotation":0,"Type":0,"HoldNumber":null,"Direction":0,"DirectionString":"N"},{"Id":0,"Holdset":null,"Description":null,"X":195,"Y":638,"Color":"0x0000FF","Rotation":0,"Type":0,"HoldNumber":null,"Direction":0,"DirectionString":"N"},{"Id":0,"Holdset":null,"Description":null,"X":295,"Y":838,"Color":"0x00FF00","Rotation":0,"Type":0,"HoldNumber":null,"Direction":0,"DirectionString":"N"},{"Id":0,"Holdset":null,"Description":null,"X":395,"Y":288,"Color":"0x0000FF","Rotation":0,"Type":0,"HoldNumber":null,"Direction":0,"DirectionString":"N"},{"Id":0,"Holdset":null,"Description":null,"X":445,"Y":86,"Color":"0xFF0000","Rotation":0,"Type":0,"HoldNumber":null,"Direction":0,"DirectionString":"N"},{"Id":0,"Holdset":null,"Description":null,"X":445,"Y":486,"Color":"0x0000FF","Rotation":0,"Type":0,"HoldNumber":null,"Direction":0,"DirectionString":"N"},{"Id":0,"Holdset":null,"Description":null,"X":445,"Y":736,"Color":"0x0000FF","Rotation":0,"Type":0,"HoldNumber":null,"Direction":0,"DirectionString":"N"},{"Id":0,"Holdset":null,"Description":null,"X":495,"Y":588,"Color":"0x0000FF","Rotation":0,"Type":0,"HoldNumber":null,"Direction":0,"DirectionString":"N"},{"Id":0,"Holdset":null,"Description":null,"X":545,"Y":86,"Color":"0xFF0000","Rotation":0,"Type":0,"HoldNumber":null,"Direction":0,"DirectionString":"N"},{"Id":0,"Holdset":null,"Description":null,"X":545,"Y":186,"Color":"0x0000FF","Rotation":0,"Type":0,"HoldNumber":null,"Direction":0,"DirectionString":"N"},{"Id":0,"Holdset":null,"Description":null,"X":545,"Y":436,"Color":"0x0000FF","Rotation":0,"Type":0,"HoldNumber":null,"Direction":0,"DirectionString":"N"}],"RepeatText":"20 climbers  have repeated this problem","NumberOfTries":null,"NameForUrl":"ml-elon-musk","Upgraded":false,"Downgraded":false,"Id":327409,"ApiId":0,"DateInserted":"\/Date(1538579851970)\/","DateUpdated":null,"DateDeleted":null,"DateTimeString":"03 Oct 2018 16:17"},{"Method":"Feet follow hands","Name":"JONAH ALT 2","Grade":"6C","UserGrade":null,"MoonBoardConfiguration":{"Id":1,"Description":"40° MoonBoard","LowGrade":null,"HighGrade":null},"MoonBoardConfigurationId":0,"Setter":{"Id":"810A4DD0-FCC1-43EC-A98F-3D9ED884E5A1","Nickname":"Jesse Firestone","Firstname":"Jesse","Lastname":"Firestone","City":"Bend","Country":"USA","ProfileImageUrl":"/Content/Account/Images/default-profile.png?637156588353564340","CanShareData":true},"FirstAscender":false,"Rating":0,"UserRating":0,"Repeats":0,"Attempts":0,"Holdsetup":{"Id":15,"Description":"MoonBoard Masters 2017","Setby":null,"DateInserted":null,"DateUpdated":null,"DateDeleted":null,"IsLocked":false,"Active":false,"Holdsets":null,"MoonBoardConfigurations":null,"HoldLayoutId":0,"AllowClimbMethods":true},"IsBenchmark":false,"IsMaster":false,"IsAssessmentProblem":false,"ProblemType":null,"Moves":[{"Id":1798400,"Description":"D5","IsStart":true,"IsEnd":false},{"Id":1798401,"Description":"F3","IsStart":true,"IsEnd":false},{"Id":1798402,"Description":"G8","IsStart":false,"IsEnd":false},{"Id":1798403,"Description":"F12","IsStart":false,"IsEnd":false},{"Id":1798404,"Description":"E14","IsStart":false,"IsEnd":false},{"Id":1798405,"Description":"C15","IsStart":false,"IsEnd":false},{"Id":1798406,"Description":"A18","IsStart":false,"IsEnd":true}],"Holdsets":null,"Locations":[{"Id":0,"Holdset":null,"Description":null,"X":95,"Y":88,"Color":"0xFF0000","Rotation":0,"Type":0,"HoldNumber":null,"Direction":0,"DirectionString":"N"},{"Id":0,"Holdset":null,"Description":null,"X":195,"Y":238,"Color":"0x0000FF","Rotation":0,"Type":0,"HoldNumber":null,"Direction":0,"DirectionString":"N"},{"Id":0,"Holdset":null,"Description":null,"X":245,"Y":736,"Color":"0x00FF00","Rotation":0,"Type":0,"HoldNumber":null,"Direction":0,"DirectionString":"N"},{"Id":0,"Holdset":null,"Description":null,"X":295,"Y":288,"Color":"0x0000FF","Rotation":0,"Type":0,"HoldNumber":null,"Direction":0,"DirectionString":"N"},{"Id":0,"Holdset":null,"Description":null,"X":345,"Y":386,"Color":"0x0000FF","Rotation":0,"Type":0,"HoldNumber":null,"Direction":0,"DirectionString":"N"},{"Id":0,"Holdset":null,"Description":null,"X":345,"Y":836,"Color":"0x00FF00","Rotation":0,"Type":0,"HoldNumber":null,"Direction":0,"DirectionString":"N"},{"Id":0,"Holdset":null,"Description":null,"X":395,"Y":588,"Color":"0x0000FF","Rotation":0,"Type":0,"HoldNumber":null,"Direction":0,"DirectionString":"N"}],"RepeatText":"Be the first to repeat this problem","NumberOfTries":null,"NameForUrl":"jonah-alt-2","Upgraded":false,"Downgraded":false,"Id":327408,"ApiId":0,"DateInserted":"\/Date(1538579644847)\/","DateUpdated":null,"DateDeleted":null,"DateTimeString":"03 Oct 2018 16:14"},{"Method":"Feet follow hands","Name":"#537 PAIN (3Q+)","Grade":"6B+","UserGrade":null,"MoonBoardConfiguration":{"Id":1,"Description":"40° MoonBoard","LowGrade":null,"HighGrade":null},"MoonBoardConfigurationId":0,"Setter":{"Id":"5E36A1D2-7544-451C-8FAD-BAED484CD5AE","Nickname":"akihiro ishii","Firstname":"akihiro","Lastname":"ishii","City":"okayama","Country":"Japan","ProfileImageUrl":"/Content/Account/Users/Profile/5E36A1D2-7544-451C-8FAD-BAED484CD5AE.jpg?637156588353720606","CanShareData":true},"FirstAscender":false,"Rating":0,"UserRating":3,"Repeats":1,"Attempts":0,"Holdsetup":{"Id":15,"Description":"MoonBoard Masters 2017","Setby":null,"DateInserted":null,"DateUpdated":null,"DateDeleted":null,"IsLocked":false,"Active":false,"Holdsets":null,"MoonBoardConfigurations":null,"HoldLayoutId":0,"AllowClimbMethods":true},"IsBenchmark":false,"IsMaster":false,"IsAssessmentProblem":false,"ProblemType":null,"Moves":[{"Id":1798368,"Description":"F4","IsStart":true,"IsEnd":false},{"Id":1798369,"Description":"E6","IsStart":false,"IsEnd":false},{"Id":1798370,"Description":"G10","IsStart":false,"IsEnd":false},{"Id":1798371,"Description":"H11","IsStart":false,"IsEnd":false},{"Id":1798372,"Description":"J11","IsStart":false,"IsEnd":false},{"Id":1798373,"Description":"H14","IsStart":false,"IsEnd":false},{"Id":1798374,"Description":"I15","IsStart":false,"IsEnd":false},{"Id":1798375,"Description":"H17","IsStart":false,"IsEnd":false},{"Id":1798376,"Description":"K18","IsStart":false,"IsEnd":true}],"Holdsets":null,"Locations":[{"Id":0,"Holdset":null,"Description":null,"X":295,"Y":688,"Color":"0x0000FF","Rotation":0,"Type":0,"HoldNumber":null,"Direction":0,"DirectionString":"N"},{"Id":0,"Holdset":null,"Description":null,"X":345,"Y":786,"Color":"0x00FF00","Rotation":0,"Type":0,"HoldNumber":null,"Direction":0,"DirectionString":"N"},{"Id":0,"Holdset":null,"Description":null,"X":395,"Y":488,"Color":"0x0000FF","Rotation":0,"Type":0,"HoldNumber":null,"Direction":0,"DirectionString":"N"},{"Id":0,"Holdset":null,"Description":null,"X":445,"Y":136,"Color":"0x0000FF","Rotation":0,"Type":0,"HoldNumber":null,"Direction":0,"DirectionString":"N"},{"Id":0,"Holdset":null,"Description":null,"X":445,"Y":286,"Color":"0x0000FF","Rotation":0,"Type":0,"HoldNumber":null,"Direction":0,"DirectionString":"N"},{"Id":0,"Holdset":null,"Description":null,"X":445,"Y":436,"Color":"0x0000FF","Rotation":0,"Type":0,"HoldNumber":null,"Direction":0,"DirectionString":"N"},{"Id":0,"Holdset":null,"Description":null,"X":495,"Y":238,"Color":"0x0000FF","Rotation":0,"Type":0,"HoldNumber":null,"Direction":0,"DirectionString":"N"},{"Id":0,"Holdset":null,"Description":null,"X":545,"Y":436,"Color":"0x0000FF","Rotation":0,"Type":0,"HoldNumber":null,"Direction":0,"DirectionString":"N"},{"Id":0,"Holdset":null,"Description":null,"X":595,"Y":88,"Color":"0xFF0000","Rotation":0,"Type":0,"HoldNumber":null,"Direction":0,"DirectionString":"N"}],"RepeatText":"1 climber  has repeated this problem","NumberOfTries":null,"NameForUrl":"-537-pain-3q","Upgraded":false,"Downgraded":false,"Id":327404,"ApiId":0,"DateInserted":"\/Date(1538573810110)\/","DateUpdated":null,"DateDeleted":null,"DateTimeString":"03 Oct 2018 14:36"},{"Method":"Feet follow hands","Name":"#536 COOL DOWN (3Q)","Grade":"6B","UserGrade":"6B","MoonBoardConfiguration":{"Id":1,"Description":"40° MoonBoard","LowGrade":null,"HighGrade":null},"MoonBoardConfigurationId":0,"Setter":{"Id":"5E36A1D2-7544-451C-8FAD-BAED484CD5AE","Nickname":"akihiro ishii","Firstname":"akihiro","Lastname":"ishii","City":"okayama","Country":"Japan","ProfileImageUrl":"/Content/Account/Users/Profile/5E36A1D2-7544-451C-8FAD-BAED484CD5AE.jpg?637156588353720606","CanShareData":true},"FirstAscender":false,"Rating":0,"UserRating":2,"Repeats":8,"Attempts":0,"Holdsetup":{"Id":15,"Description":"MoonBoard Masters 2017","Setby":null,"DateInserted":null,"DateUpdated":null,"DateDeleted":null,"IsLocked":false,"Active":false,"Holdsets":null,"MoonBoardConfigurations":null,"HoldLayoutId":0,"AllowClimbMethods":true},"IsBenchmark":false,"IsMaster":false,"IsAssessmentProblem":false,"ProblemType":null,"Moves":[{"Id":1798359,"Description":"E6","IsStart":false,"IsEnd":false},{"Id":1798360,"Description":"G10","IsStart":false,"IsEnd":false},{"Id":1798361,"Description":"F4","IsStart":true,"IsEnd":false},{"Id":1798362,"Description":"E12","IsStart":false,"IsEnd":false},{"Id":1798363,"Description":"F13","IsStart":false,"IsEnd":false},{"Id":1798364,"Description":"D15","IsStart":false,"IsEnd":false},{"Id":1798365,"Description":"G16","IsStart":false,"IsEnd":false},{"Id":1798366,"Description":"H16","IsStart":false,"IsEnd":false},{"Id":1798367,"Description":"J18","IsStart":false,"IsEnd":true}],"Holdsets":null,"Locations":[{"Id":0,"Holdset":null,"Description":null,"X":245,"Y":236,"Color":"0x0000FF","Rotation":0,"Type":0,"HoldNumber":null,"Direction":0,"DirectionString":"N"},{"Id":0,"Holdset":null,"Description":null,"X":295,"Y":688,"Color":"0x0000FF","Rotation":0,"Type":0,"HoldNumber":null,"Direction":0,"DirectionString":"N"},{"Id":0,"Holdset":null,"Description":null,"X":295,"Y":388,"Color":"0x0000FF","Rotation":0,"Type":0,"HoldNumber":null,"Direction":0,"DirectionString":"N"},{"Id":0,"Holdset":null,"Description":null,"X":345,"Y":336,"Color":"0x0000FF","Rotation":0,"Type":0,"HoldNumber":null,"Direction":0,"DirectionString":"N"},{"Id":0,"Holdset":null,"Description":null,"X":345,"Y":786,"Color":"0x00FF00","Rotation":0,"Type":0,"HoldNumber":null,"Direction":0,"DirectionString":"N"},{"Id":0,"Holdset":null,"Description":null,"X":395,"Y":488,"Color":"0x0000FF","Rotation":0,"Type":0,"HoldNumber":null,"Direction":0,"DirectionString":"N"},{"Id":0,"Holdset":null,"Description":null,"X":395,"Y":188,"Color":"0x0000FF","Rotation":0,"Type":0,"HoldNumber":null,"Direction":0,"DirectionString":"N"},{"Id":0,"Holdset":null,"Description":null,"X":445,"Y":186,"Color":"0x0000FF","Rotation":0,"Type":0,"HoldNumber":null,"Direction":0,"DirectionString":"N"},{"Id":0,"Holdset":null,"Description":null,"X":545,"Y":86,"Color":"0xFF0000","Rotation":0,"Type":0,"HoldNumber":null,"Direction":0,"DirectionString":"N"}],"RepeatText":"8 climbers  have repeated this problem","NumberOfTries":null,"NameForUrl":"-536-cool-down-3q","Upgraded":false,"Downgraded":false,"Id":327403,"ApiId":0,"DateInserted":"\/Date(1538573160060)\/","DateUpdated":null,"DateDeleted":null,"DateTimeString":"03 Oct 2018 14:26"}],"Total":26320,"AggregateResults":null,"Errors":null}